Workbook

Sheet Aid recipients
A1: ﻿Country | B1: Another Beneficiary Member State | C1: Aid Measure Title | D1: Aid Measure Title [EN] | E1: SA.Number | F1: Ref-no. | G1: National ID | H1: Name of the beneficiary | I1: Name of the beneficiary [EN] | J1: Beneficiary Type | K1: Region | L1: Sector (NACE) | M1: Aid Instrument | N1: Objectives of the Aid | O1: Aid element, expressed as full amount | P1: Currency | Q1: Date of granting | R1: Granting Authority Name | S1: Granting Authority Name [EN] | T1: Published Date
A2: Latvia | B2: Latvia | C2: Atbalsts ieguldījumiem ražošanas telpu un infrastruktūras izveidei vai rekonstrukcijai | D2: Aid for investments for the construction or reconstruction of industrial premises and infrastructure | E2: SA.45422 | F2: TM-10001476 | G2: 50003428031 | H2: Mārupes Metālmeistars | I2: Marupes metālmeistars | J2: Small and medium-sized entreprises | K2: Latvija | L2: Manufacture of other fabricated metal products n.e.c. | M2: Direct grant/ Interest rate subsidy | N2: Regional aid - investment aid (Art. 14) - Scheme | O2: 799480.74 | P2: EUR | Q2: 42677 | R2: Centrālā finanšu un līgumu aģentūra | S2: Central Finance and Contracting Agency | T2: 42724
A3: Latvia | B3: Latvia | C3: Atbalsts ieguldījumiem ražošanas telpu un infrastruktūras izveidei vai rekonstrukcijai | D3: Aid for investments for the construction or reconstruction of industrial premises and infrastructure | E3: SA.45422 | F3: TM-10001481 | G3: 50103186141 | H3: TECNOPALI NORTH EUROPE | I3: TECNOPALI NORTH EUROPE | J3: Small and medium-sized entreprises | K3: Latvija | L3: Manufacture of metal structures and parts of structures | M3: Direct grant/ Interest rate subsidy | N3: Regional aid - investment aid (Art. 14) - Scheme | O3: 833058.47 | P3: EUR | Q3: 42677 | R3: Centrālā finanšu un līgumu aģentūra | S3: Central Finance and Contracting Agency | T3: 42724
A4: Latvia | B4: Latvia | C4: Atbalsts ieguldījumiem ražošanas telpu un infrastruktūras izveidei vai rekonstrukcijai | D4: Aid for investments for the construction or reconstruction of industrial premises and infrastructure | E4: SA.45422 | F4: TM-10001472 | G4: 90000284085 | H4: Ventspils Brīvostas pārvalde | I4: Ventspils Free Port Authority | J4: Only large enterprises | K4: Latvija | L4: Service activities incidental to water transportation | M4: Direct grant/ Interest rate subsidy | N4: Regional aid - investment aid (Art. 14) - Scheme | O4: 1165802.83 | P4: EUR | Q4: 42677 | R4: Centrālā finanšu un līgumu aģentūra | S4: Central Finance and Contracting Agency | T4: 42724
A5: Latvia | B5: Latvia | C5: Atbalsts ieguldījumiem ražošanas telpu un infrastruktūras izveidei vai rekonstrukcijai | D5: Aid for investments for the construction or reconstruction of industrial premises and infrastructure | E5: SA.45422 | F5: TM-10001480 | G5: 40003294211 | H5: Tukuma Piens | I5: Tukums Milk | J5: Small and medium-sized entreprises | K5: Latvija | L5: Operation of dairies and cheese making | M5: Direct grant/ Interest rate subsidy | N5: Regional aid - investment aid (Art. 14) - Scheme | O5: 964778.3 | P5: EUR | Q5: 42706 | R5: Centrālā finanšu un līgumu aģentūra | S5: Central Finance and Contracting Agency | T5: 42724
A6: Latvia | B6: Latvia | C6: Atbalsts ieguldījumiem ražošanas telpu un infrastruktūras izveidei vai rekonstrukcijai | D6: Aid for investments for the construction or reconstruction of industrial premises and infrastructure | E6: SA.45422 | F6: TM-10001470 | G6: 42103073886 | H6: Vecās Ostmalas Biznesa Parks | I6: Old Ostmalas Business Parks | J6: Small and medium-sized entreprises | K6: Latvija | L6: Rental and operating of own or leased real estate | M6: Direct grant/ Interest rate subsidy | N6: Regional aid - investment aid (Art. 14) - Scheme | O6: 582594.57 | P6: EUR | Q6: 42706 | R6: Centrālā finanšu un līgumu aģentūra | S6: Central Finance and Contracting Agency | T6: 42724
A7: Latvia | B7: Latvia | C7: Atbalsts ieguldījumiem ražošanas telpu un infrastruktūras izveidei vai rekonstrukcijai | D7: Aid for investments for the construction or reconstruction of industrial premises and infrastructure | E7: SA.45422 | F7: TM-10001479 | G7: 40203003707 | H7: TRAPI | I7: LADDERS | J7: Small and medium-sized entreprises | K7: Latvija | L7: Rental and operating of own or leased real estate | M7: Direct grant/ Interest rate subsidy | N7: Regional aid - investment aid (Art. 14) - Scheme | O7: 1166000 | P7: EUR | Q7: 42706 | R7: Centrālā finanšu un līgumu aģentūra | S7: Central Finance and Contracting Agency | T7: 42724
A8: Latvia | B8: Latvia | C8: Atbalsts ieguldījumiem ražošanas telpu un infrastruktūras izveidei vai rekonstrukcijai | D8: Aid for investments for the construction or reconstruction of industrial premises and infrastructure | E8: SA.45422 | F8: TM-10065234 | G8: 90000284085 | H8: Ventspils Brīvostas pārvalde | I8: Ventspils Free Port Authority | J8: Only large enterprises | K8: Kurzeme | L8: Service activities incidental to water transportation | M8: Direct grant/ Interest rate subsidy | N8: Regional aid - investment aid (Art. 14) - Scheme | O8: 1165839.59 | P8: EUR | Q8: 42731 | R8: Centrālā finanšu un līgumu aģentūra | S8: Central Finance and Contracting Agency | T8: 42912
A9: Latvia | B9: Latvia | C9: Atbalsts ieguldījumiem ražošanas telpu un infrastruktūras izveidei vai rekonstrukcijai | D9: Aid for investments for the construction or reconstruction of industrial premises and infrastructure | E9: SA.45422 | F9: TM-10065240 | G9: 40203006027 | H9: GP TEHNOPARKI | I9: GP TEHNOPARKI | J9: Small and medium-sized entreprises | K9: Pierīga | L9: Rental and operating of own or leased real estate | M9: Direct grant/ Interest rate subsidy | N9: Regional aid - investment aid (Art. 14) - Scheme | O9: 1146555.6 | P9: EUR | Q9: 42731 | R9: Centrālā finanšu un līgumu aģentūra | S9: Central Finance and Contracting Agency | T9: 42912
A10: Latvia | B10: Latvia | C10: Atbalsts ieguldījumiem ražošanas telpu un infrastruktūras izveidei vai rekonstrukcijai | D10: Aid for investments for the construction or reconstruction of industrial premises and infrastructure | E10: SA.45422 | F10: TM-10065241 | G10: 40103748266 | H10: NTC INVESTĪCIJAS | I10: THE NTC INVESTMENT | J10: Small and medium-sized entreprises | K10: Vidzeme | L10: Rental and operating of own or leased real estate | M10: Direct grant/ Interest rate subsidy | N10: Regional aid - investment aid (Art. 14) - Scheme | O10: 628631.66 | P10: EUR | Q10: 42731 | R10: Centrālā finanšu un līgumu aģentūra | S10: Central Finance and Contracting Agency | T10: 42912
A11: Latvia | B11: Latvia | C11: Atbalsts ieguldījumiem ražošanas telpu un infrastruktūras izveidei vai rekonstrukcijai | D11: Aid for investments for the construction or reconstruction of industrial premises and infrastructure | E11: SA.45422 | F11: TM-10065236 | G11: 90000284085 | H11: Ventspils Brīvostas pārvalde | I11: Ventspils Free Port Authority | J11: Only large enterprises | K11: Kurzeme | L11: Service activities incidental to water transportation | M11: Direct grant/ Interest rate subsidy | N11: Regional aid - investment aid (Art. 14) - Scheme | O11: 1165752.18 | P11: EUR | Q11: 42731 | R11: Centrālā finanšu un līgumu aģentūra | S11: Central Finance and Contracting Agency | T11: 42912
A12: Latvia | B12: Latvia | C12: Atbalsts ieguldījumiem ražošanas telpu un infrastruktūras izveidei vai rekonstrukcijai | D12: Aid for investments for the construction or reconstruction of industrial premises and infrastructure | E12: SA.45422 | F12: TM-10065239 | G12: 45103000023 | H12: TENAX | I12: TENAX | J12: Small and medium-sized entreprises | K12: Zemgale | L12: Rental and operating of own or leased real estate | M12: Direct grant/ Interest rate subsidy | N12: Regional aid - investment aid (Art. 14) - Scheme | O12: 1166000 | P12: EUR | Q12: 42731 | R12: Centrālā finanšu un līgumu aģentūra | S12: Central Finance and Contracting Agency | T12: 42912
A13: Latvia | B13: Latvia | C13: Atbalsts ieguldījumiem ražošanas telpu un infrastruktūras izveidei vai rekonstrukcijai | D13: Aid for investments for the construction or reconstruction of industrial premises and infrastructure | E13: SA.45422 | F13: TM-10065238 | G13: 40103563278 | H13: IT INTERNATIONAL | I13: IN INTERNATIONAL | J13: Small and medium-sized entreprises | K13: Latgale | L13: Sawmilling and planing of wood | M13: Direct grant/ Interest rate subsidy | N13: Regional aid - investment aid (Art. 14) - Scheme | O13: 681010.03 | P13: EUR | Q13: 42731 | R13: Centrālā finanšu un līgumu aģentūra | S13: Central Finance and Contracting Agency | T13: 42912
... A15: Latvia | B15: Latvia | C15: Atbalsts ieguldījumiem ražošanas telpu un infrastruktūras izveidei vai rekonstrukcijai | D15: Aid for investments for the construction or reconstruction of industrial premises and infrastructure | E15: SA.45422 | F15: TM-10065266 | G15: 40003822806 | H15: Lyngson | I15: Lyngson | J15: Small and medium-sized entreprises | K15: Pierīga | L15: Manufacture of central heating radiators and boilers | M15: Direct grant/ Interest rate subsidy | N15: Regional aid - investment aid (Art. 14) - Scheme | O15: 798750 | P15: EUR | Q15: 42760 | R15: Centrālā finanšu un līgumu aģentūra | S15: Central Finance and Contracting Agency | T15: 42913
A16: Latvia | B16: Latvia | C16: Atbalsts ieguldījumiem ražošanas telpu un infrastruktūras izveidei vai rekonstrukcijai | D16: Aid for investments for the construction or reconstruction of industrial premises and infrastructure | E16: SA.45422 | F16: TM-10065261 | G16: 40003199078 | H16: Piebalgas | I16: Piebalgas | J16: Small and medium-sized entreprises | K16: Zemgale | L16: Sawmilling and planing of wood | M16: Direct grant/ Interest rate subsidy | N16: Regional aid - investment aid (Art. 14) - Scheme | O16: 512510 | P16: EUR | Q16: 42760 | R16: Centrālā finanšu un līgumu aģentūra | S16: Central Finance and Contracting Agency | T16: 42913
A17: Latvia | B17: Latvia | C17: Atbalsts ieguldījumiem ražošanas telpu un infrastruktūras izveidei vai rekonstrukcijai | D17: Aid for investments for the construction or reconstruction of industrial premises and infrastructure | E17: SA.45422 | F17: TM-10065265 | G17: 40003479924 | H17: Kronus | I17: Kronus | J17: Small and medium-sized entreprises | K17: Pierīga | L17: Manufacture of wooden containers | M17: Direct grant/ Interest rate subsidy | N17: Regional aid - investment aid (Art. 14) - Scheme | O17: 810306 | P17: EUR | Q17: 42760 | R17: Centrālā finanšu un līgumu aģentūra | S17: Central Finance and Contracting Agency | T17: 42913
A18: Latvia | B18: Latvia | C18: Atbalsts ieguldījumiem ražošanas telpu un infrastruktūras izveidei vai rekonstrukcijai | D18: Aid for investments for the construction or reconstruction of industrial premises and infrastructure | E18: SA.45422 | F18: TM-10065262 | G18: 42103060434 | H18: NPK Expert | I18: NPK Expert | J18: Small and medium-sized entreprises | K18: Kurzeme | L18: Manufacture of fertilisers and nitrogen compounds | M18: Direct grant/ Interest rate subsidy | N18: Regional aid - investment aid (Art. 14) - Scheme | O18: 627697 | P18: EUR | Q18: 42769 | R18: Centrālā finanšu un līgumu aģentūra | S18: Central Finance and Contracting Agency | T18: 42913
A19: Latvia | B19: Latvia | C19: Atbalsts ieguldījumiem ražošanas telpu un infrastruktūras izveidei vai rekonstrukcijai | D19: Aid for investments for the construction or reconstruction of industrial premises and infrastructure | E19: SA.45422 | F19: TM-10065264 | G19: 40003919987 | H19: EcoLead | I19: EcoLead | J19: Small and medium-sized entreprises | K19: Zemgale | L19: Lead, zinc and tin production | M19: Direct grant/ Interest rate subsidy | N19: Regional aid - investment aid (Art. 14) - Scheme | O19: 560700 | P19: EUR | Q19: 42769 | R19: Centrālā finanšu un līgumu aģentūra | S19: Central Finance and Contracting Agency | T19: 42913
A20: Latvia | B20: Latvia | C20: Atbalsts ieguldījumiem ražošanas telpu un infrastruktūras izveidei vai rekonstrukcijai | D20: Aid for investments for the construction or reconstruction of industrial premises and infrastructure | E20: SA.45422 | F20: TM-10080807 | G20: 40103702152 | H20: Carbon energy systems | I20: Carbon energy systems | J20: Small and medium-sized entreprises | K20: Vidzeme | L20: Manufacture of other organic basic chemicals | M20: Direct grant/ Interest rate subsidy | N20: Regional aid - investment aid (Art. 14) - Scheme | O20: 623040.77 | P20: EUR | Q20: 42993 | R20: Centrālā finanšu un līgumu aģentūra | S20: Central Finance and Contracting Agency | T20: 43007
A21: Latvia | B21: Latvia | C21: Atbalsts ieguldījumiem ražošanas telpu un infrastruktūras izveidei vai rekonstrukcijai | D21: Aid for investments for the construction or reconstruction of industrial premises and infrastructure | E21: SA.45422 | F21: TM-10171220 | G21: 45403003160 | H21: JĒKABPILS PMK | I21: JĒKABPILS PNK | J21: Small and medium-sized entreprises | K21: Latvija | L21: Construction of residential and non-residential buildings | M21: Direct grant/ Interest rate subsidy | N21: Regional aid - investment aid (Art. 14) - Scheme | O21: 735300 | P21: EUR | Q21: 43707 | R21: Centrālā finanšu un līgumu aģentūra | S21: Central Finance and Contracting Agency | T21: 43733
A22: Latvia | B22: Latvia | C22: Atbalsts ieguldījumiem ražošanas telpu un infrastruktūras izveidei vai rekonstrukcijai | D22: Aid for investments for the construction or reconstruction of industrial premises and infrastructure | E22: SA.45422 | F22: TM-10171221 | G22: 40203021261 | H22: AmberBirch | I22: AmberBirch | J22: Small and medium-sized entreprises | K22: Latvija | L22: Manufacture of veneer sheets and wood-based panels | M22: Direct grant/ Interest rate subsidy | N22: Regional aid - investment aid (Art. 14) - Scheme | O22: 1500000 | P22: EUR | Q22: 43720 | R22: Centrālā finanšu un līgumu aģentūra | S22: Central Finance and Contracting Agency | T22: 43733
A23: Latvia | B23: Latvia | C23: Atbalsts ieguldījumiem ražošanas telpu un infrastruktūras izveidei vai rekonstrukcijai | D23: Aid for investments for the construction or reconstruction of industrial premises and infrastructure | E23: SA.45422 | F23: TM-10182047 | G23: 40003752458 | H23: VALMIERMUIŽAS ALUS | I23: VALMIERMUNIIC BEER | J23: Small and medium-sized entreprises | K23: Latvija | L23: Manufacture of beer | M23: Direct grant/ Interest rate subsidy | N23: Regional aid - investment aid (Art. 14) - Scheme | O23: 1307155 | P23: EUR | Q23: 43734 | R23: Centrālā finanšu un līgumu aģentūra | S23: Central Finance and Contracting Agency | T23: 43845
A24: Latvia | B24: Latvia | C24: Atbalsts ieguldījumiem ražošanas telpu un infrastruktūras izveidei vai rekonstrukcijai | D24: Aid for investments for the construction or reconstruction of industrial premises and infrastructure | E24: SA.45422 | F24: TM-10182086 | G24: 42103021136 | H24: PUMAC LIEPAJA | I24: PUMAC LAYER | J24: Small and medium-sized entreprises | K24: Latvija | L24: Rental and operating of own or leased real estate | M24: Direct grant/ Interest rate subsidy | N24: Regional aid - investment aid (Art. 14) - Scheme | O24: 1500000 | P24: EUR | Q24: 43734 | R24: Centrālā finanšu un līgumu aģentūra | S24: Central Finance and Contracting Agency | T24: 43845
A25: Latvia | B25: Latvia | C25: Atbalsts ieguldījumiem ražošanas telpu un infrastruktūras izveidei vai rekonstrukcijai | D25: Aid for investments for the construction or reconstruction of industrial premises and infrastructure | E25: SA.45422 | F25: TM-10182088 | G25: 45403042702 | H25: CEWOOD | I25: CEWOOD | J25: Small and medium-sized entreprises | K25: Latvija | L25: Manufacture of fibre cement | M25: Direct grant/ Interest rate subsidy | N25: Regional aid - investment aid (Art. 14) - Scheme | O25: 1124985.15 | P25: EUR | Q25: 43759 | R25: Centrālā finanšu un līgumu aģentūra | S25: Central Finance and Contracting Agency | T25: 43845
A26: Latvia | B26: Latvia | C26: Atbalsts ieguldījumiem ražošanas telpu un infrastruktūras izveidei vai rekonstrukcijai | D26: Aid for investments for the construction or reconstruction of industrial premises and infrastructure | E26: SA.45422 | F26: TM-10182089 | G26: 54103005451 | H26: VUDLANDE | I26: ﻿VUDLANDE | J26: Small and medium-sized entreprises | K26: Latvija | L26: Sawmilling and planing of wood | M26: Direct grant/ Interest rate subsidy | N26: Regional aid - investment aid (Art. 14) - Scheme | O26: 919509.28 | P26: EUR | Q26: 43759 | R26: Centrālā finanšu un līgumu aģentūra | S26: Central Finance and Contracting Agency | T26: 43845
A27: Latvia | B27: Latvia | C27: Atbalsts ieguldījumiem ražošanas telpu un infrastruktūras izveidei vai rekonstrukcijai | D27: Aid for investments for the construction or reconstruction of industrial premises and infrastructure | E27: SA.45422 | F27: TM-10182090 | G27: 40103299681 | H27: Artex Latvia | I27: Artex Latvia | J27: Small and medium-sized entreprises | K27: Latvija | L27: Manufacture of made-up textile articles, except apparel | M27: Direct grant/ Interest rate subsidy | N27: Regional aid - investment aid (Art. 14) - Scheme | O27: 769624.54 | P27: EUR | Q27: 43766 | R27: Centrālā finanšu un līgumu aģentūra | S27: Central Finance and Contracting Agency | T27: 43845
A28: Latvia | B28: Latvia | C28: Atbalsts ieguldījumiem ražošanas telpu un infrastruktūras izveidei vai rekonstrukcijai | D28: Aid for investments for the construction or reconstruction of industrial premises and infrastructure | E28: SA.45422 | F28: TM-10195045 | G28: 40103318408 | H28: SFM Latvia | I28: SFM Latvia | J28: Small and medium-sized entreprises | K28: Latvija | L28: Manufacture of metal structures and parts of structures | M28: Direct grant/ Interest rate subsidy | N28: Regional aid - investment aid (Art. 14) - Scheme | O28: 1175655.96 | P28: EUR | Q28: 43812 | R28: Centrālā finanšu un līgumu aģentūra | S28: Central Finance and Contracting Agency | T28: 43924
... A37: Latvia | B37: Latvia | C37: Atbalsts ieguldījumiem ražošanas telpu un infrastruktūras izveidei vai rekonstrukcijai | D37: Aid for investments for the construction or reconstruction of industrial premises and infrastructure | E37: SA.45422 | F37: TM-10269935 | G37: 40103590897 | H37: VIZULO | I37: MR VIZULO | J37: Small and medium-sized entreprises | K37: Latvija | L37: Manufacture of electric lighting equipment | M37: Direct grant/ Interest rate subsidy | N37: Regional aid - investment aid (Art. 14) - Scheme | O37: 1096914.58 | P37: EUR | Q37: 44225 | R37: Centrālā finanšu un līgumu aģentūra | S37: Central Finance and Contracting Agency | T37: 44281
N39: total | O39: =O2+O3+O4+O5+O6+O7+O8+O9+O10+O11+O12+O13+O14+O15+O16+O17+O18+O19+O20+O21+O22+O23+O24+O25+O26+O27+O28+O29+O30+O31+O32+O33+O34+O35+O36+O37 -> 35761225
O40: 35761225
Q42: Cost per job created
N43: employee dif in T1 | O43: =Employees!AE31-Employees!AD31 -> 97 | Q43: =O39/O43 -> 368672.42
O44: =Employees!AF31-Employees!AD31 -> 398 | Q44: =O39/O44 -> 89852.324
O45: =Employees!AG31-Employees!AD31 -> 513 | Q45: =O39/O45 -> 69709.99

Sheet Firm list
A1: ID | B1: Name | C1: NACE | D1: Website | E1: Notes | F1: Employees | G1: Tangible assets | H1: Yearly sales | I1: Investment | J1: Wages | K1: Total available
A2: 1 | B2: Mārupes Metālmeistars | C2: 25.4 | D2: https://www.metalmaster.lv/eng | E2: - | F2: =Employees!O2 -> Yes | G2: ='Tangible assets'!O2 -> Yes | H2: ='Yearly Sales'!O2 -> Yes | I2: ='Investment (capex)'!O2 -> Yes | J2: ='Wages salaries'!O2 -> Yes | K2: =COUNTIF(F2:J2,"yes") -> 5
A3: =A2+1 -> 2 | B3: TECNOPALI NORTH EUROPE | C3: 25.11 | D3: https://www.tecnopali.lv/ | E3: - | F3: =Employees!O3 -> Yes | G3: ='Tangible assets'!O3 -> Yes | H3: ='Yearly Sales'!O3 -> Yes | I3: ='Investment (capex)'!O3 -> No | J3: ='Wages salaries'!O3 -> Yes | K3: =COUNTIF(F3:J3,"yes") -> 4
A4: =A3+1 -> 3 | B4: Ventspils Brīvostas pārvalde | C4: 50.2 | D4: https://www.portofventspils.lv/lv/brivostas-parvalde/ | E4: No employee numbers in 2017-2013 | F4: =Employees!O4 -> No | G4: ='Tangible assets'!O4 -> Yes | H4: ='Yearly Sales'!O4 -> Yes | I4: ='Investment (capex)'!O4 -> No | J4: ='Wages salaries'!O4 -> No | K4: =COUNTIF(F4:J4,"yes") -> 2
A5: =A4+1 -> 4 | B5: Tukuma Piens | C5: 10.51 | D5: https://baltais.lv/?lang=en | E5: - | F5: =Employees!O5 -> Yes | G5: ='Tangible assets'!O5 -> Yes | H5: ='Yearly Sales'!O5 -> Yes | I5: ='Investment (capex)'!O5 -> Yes | J5: ='Wages salaries'!O5 -> Yes | K5: =COUNTIF(F5:J5,"yes") -> 5
A6: =A5+1 -> 5 | B6: Vecās Ostmalas Biznesa Parks | C6: 68.2 | D6: https://vobp.lv/ | E6: Almost no employees | F6: =Employees!O6 -> Yes | G6: ='Tangible assets'!O6 -> No | H6: ='Yearly Sales'!O6 -> No | I6: ='Investment (capex)'!O6 -> No | J6: ='Wages salaries'!O6 -> No | K6: =COUNTIF(F6:J6,"yes") -> 1
A7: =A6+1 -> 6 | B7: TRAPI | C7: 41.2 | D7: NA | E7: Almost no employees | F7: =Employees!O7 -> No | G7: ='Tangible assets'!O7 -> No | H7: ='Yearly Sales'!O7 -> No | I7: ='Investment (capex)'!O7 -> No | J7: ='Wages salaries'!O7 -> No | K7: =COUNTIF(F7:J7,"yes") -> 0
A8: =A7+1 -> 7 | B8: GP TEHNOPARKI | C8: 68.2 | D8: NA | E8: Almost no employees | F8: =Employees!O8 -> No | G8: ='Tangible assets'!O8 -> No | H8: ='Yearly Sales'!O8 -> No | I8: ='Investment (capex)'!O8 -> No | J8: ='Wages salaries'!O8 -> No | K8: =COUNTIF(F8:J8,"yes") -> 0
A9: =A8+1 -> 8 | B9: NTC INVESTĪCIJAS | C9: 68.2 | D9: NA | E9: Reports zero employees | F9: =Employees!O9 -> No | G9: ='Tangible assets'!O9 -> Yes | H9: ='Yearly Sales'!O9 -> Yes | I9: ='Investment (capex)'!O9 -> No | J9: ='Wages salaries'!O9 -> No | K9: =COUNTIF(F9:J9,"yes") -> 2
A10: =A9+1 -> 9 | B10: TENAX | C10: 23.66 | D10: https://tenaxpanel.lv/lv/ | E10: - | F10: =Employees!O10 -> Yes | G10: ='Tangible assets'!O10 -> No | H10: ='Yearly Sales'!O10 -> Yes | I10: ='Investment (capex)'!O10 -> Yes | J10: ='Wages salaries'!O10 -> Yes | K10: =COUNTIF(F10:J10,"yes") -> 4
A11: =A10+1 -> 10 | B11: IT INTERNATIONAL | C11: 62.1 | D11: https://company.lursoft.lv/en/international-it-latvia/41503088322 | E11: Liquidated | F11: =Employees!O11 -> No | G11: ='Tangible assets'!O11 -> No | H11: ='Yearly Sales'!O11 -> No | I11: ='Investment (capex)'!O11 -> No | J11: ='Wages salaries'!O11 -> No | K11: =COUNTIF(F11:J11,"yes") -> 0
A12: =A11+1 -> 11 | B12: iCotton | C12: 20.42 | D12: https://www.icotton.eu/ | E12: - | F12: =Employees!O12 -> Yes | G12: ='Tangible assets'!O12 -> Yes | H12: ='Yearly Sales'!O12 -> Yes | I12: ='Investment (capex)'!O12 -> Yes | J12: ='Wages salaries'!O12 -> Yes | K12: =COUNTIF(F12:J12,"yes") -> 5
A13: =A12+1 -> 12 | B13: Lyngson | C13: 25.21 | D13: https://lyngson.lv/ | E13: - | F13: =Employees!O13 -> Yes | G13: ='Tangible assets'!O13 -> Yes | H13: ='Yearly Sales'!O13 -> Yes | I13: ='Investment (capex)'!O13 -> Yes | J13: ='Wages salaries'!O13 -> Yes | K13: =COUNTIF(F13:J13,"yes") -> 5
A14: =A13+1 -> 13 | B14: Piebalgas | C14: 46.13 or 16.11 | D14: https://www.piebalgas.lv/ | E14: - | F14: =Employees!O14 -> Yes | G14: ='Tangible assets'!O14 -> Yes | H14: ='Yearly Sales'!O14 -> Yes | I14: ='Investment (capex)'!O14 -> No | J14: ='Wages salaries'!O14 -> Yes | K14: =COUNTIF(F14:J14,"yes") -> 4
A15: =A14+1 -> 14 | B15: Kronus | C15: 16.24 or 16.12 | D15: https://www.kronus.eu/lv/ | E15: - | F15: =Employees!O15 -> Yes | G15: ='Tangible assets'!O15 -> Yes | H15: ='Yearly Sales'!O15 -> Yes | I15: ='Investment (capex)'!O15 -> Yes | J15: ='Wages salaries'!O15 -> Yes | K15: =COUNTIF(F15:J15,"yes") -> 5
A16: =A15+1 -> 15 | B16: NPK Expert | C16: 20.15 | D16: https://www.npkexpert.com/ | E16: Collapsed and went bankrupt in late 2019 | F16: =Employees!O16 -> No | G16: ='Tangible assets'!O16 -> No | H16: ='Yearly Sales'!O16 -> No | I16: ='Investment (capex)'!O16 -> No | J16: ='Wages salaries'!O16 -> No | K16: =COUNTIF(F16:J16,"yes") -> 0
A17: =A16+1 -> 16 | B17: EcoLead | C17: 46.87 | D17: https://ecolead.lv/lv/ | E17: - | F17: =Employees!O17 -> Yes | G17: ='Tangible assets'!O17 -> Yes | H17: ='Yearly Sales'!O17 -> No | I17: ='Investment (capex)'!O17 -> No | J17: ='Wages salaries'!O17 -> No | K17: =COUNTIF(F17:J17,"yes") -> 2
A18: =A17+1 -> 17 | B18: Carbon energy systems | C18: 19.1 | D18: NA | E18: - | F18: =Employees!O18 -> Yes | G18: ='Tangible assets'!O18 -> No | H18: ='Yearly Sales'!O18 -> No | I18: ='Investment (capex)'!O18 -> No | J18: ='Wages salaries'!O18 -> No | K18: =COUNTIF(F18:J18,"yes") -> 1
A19: =A18+1 -> 18 | B19: JĒKABPILS PMK | C19: 41 | D19: https://jpmk.lv/ | E19: - | F19: =Employees!O19 -> Yes | G19: ='Tangible assets'!O19 -> Yes | H19: ='Yearly Sales'!O19 -> Yes | I19: ='Investment (capex)'!O19 -> Yes | J19: ='Wages salaries'!O19 -> Yes | K19: =COUNTIF(F19:J19,"yes") -> 5
A20: =A19+1 -> 19 | B20: AmberBirch | C20: 16.21 | D20: https://amberbirch.lv/ | E20: - | F20: =Employees!O20 -> No | G20: ='Tangible assets'!O20 -> Yes | H20: ='Yearly Sales'!O20 -> No | I20: ='Investment (capex)'!O20 -> No | J20: ='Wages salaries'!O20 -> Yes | K20: =COUNTIF(F20:J20,"yes") -> 2
A21: =A20+1 -> 20 | B21: VALMIERMUIŽAS ALUS | C21: 11.05 | D21: https://valmiermuiza.lv/ | E21: - | F21: =Employees!O21 -> Yes | G21: ='Tangible assets'!O21 -> Yes | H21: ='Yearly Sales'!O21 -> Yes | I21: ='Investment (capex)'!O21 -> Yes | J21: ='Wages salaries'!O21 -> Yes | K21: =COUNTIF(F21:J21,"yes") -> 5
A22: =A21+1 -> 21 | B22: PUMAC LIEPAJA | C22: 68.2 | D22: NA | E22: - | F22: =Employees!O22 -> Yes | G22: ='Tangible assets'!O22 -> Yes | H22: ='Yearly Sales'!O22 -> Yes | I22: ='Investment (capex)'!O22 -> No | J22: ='Wages salaries'!O22 -> Yes | K22: =COUNTIF(F22:J22,"yes") -> 4
A23: =A22+1 -> 22 | B23: CEWOOD | C23: 23.65 or 16.10 or 23.65 | D23: https://www.cewood.com/lv | E23: I need 2020 (for year 2019) pieskats because they must have the salary numbers | F23: =Employees!O23 -> Yes | G23: ='Tangible assets'!O23 -> No | H23: ='Yearly Sales'!O23 -> Yes | I23: ='Investment (capex)'!O23 -> No | J23: ='Wages salaries'!O23 -> No | K23: =COUNTIF(F23:J23,"yes") -> 2
A24: =A23+1 -> 23 | B24: VUDLANDE | C24: 16.11 | D24: https://www.vudlande.lv/ | E24: - | F24: =Employees!O24 -> Yes | G24: ='Tangible assets'!O24 -> Yes | H24: ='Yearly Sales'!O24 -> Yes | I24: ='Investment (capex)'!O24 -> Yes | J24: ='Wages salaries'!O24 -> Yes | K24: =COUNTIF(F24:J24,"yes") -> 5
A25: =A24+1 -> 24 | B25: Artex Latvia | C25: 13.92 | D25: https://www.artex.se/smiltene-latvia | E25: - | F25: =Employees!O25 -> Yes | G25: ='Tangible assets'!O25 -> No | H25: ='Yearly Sales'!O25 -> Yes | I25: ='Investment (capex)'!O25 -> No | J25: ='Wages salaries'!O25 -> Yes | K25: =COUNTIF(F25:J25,"yes") -> 3
A26: =A25+1 -> 25 | B26: SFM Latvia | C26: 25.11 | D26: https://sfm.lv/ | E26: Missing wages in 2017 | F26: =Employees!O26 -> Yes | G26: ='Tangible assets'!O26 -> No | H26: ='Yearly Sales'!O26 -> Yes | I26: ='Investment (capex)'!O26 -> No | J26: ='Wages salaries'!O26 -> No | K26: =COUNTIF(F26:J26,"yes") -> 2
A27: =A26+1 -> 26 | B27: EB Liepāja | C27: 68.2 or 41 | D27: NA | E27: Liquidated, was a subsidiary of the STATS Group | F27: =Employees!O27 -> No | G27: ='Tangible assets'!O27 -> No | H27: ='Yearly Sales'!O27 -> No | I27: ='Investment (capex)'!O27 -> No | J27: ='Wages salaries'!O27 -> No | K27: =COUNTIF(F27:J27,"yes") -> 0
A28: =A27+1 -> 27 | B28: Stiga RM | C28: 16.21 or 2.2 | D28: https://stigarm.lv/lv/ | E28: - | F28: =Employees!O28 -> Yes | G28: ='Tangible assets'!O28 -> Yes | H28: ='Yearly Sales'!O28 -> Yes | I28: ='Investment (capex)'!O28 -> Yes | J28: ='Wages salaries'!O28 -> Yes | K28: =COUNTIF(F28:J28,"yes") -> 5
A29: =A28+1 -> 28 | B29: Haugaard Baltic | C29: 31 | D29: https://www.haugaard.eu/ | E29: Operates at a loss, moved to a new factory in 2023-24 | F29: =Employees!O29 -> Yes | G29: ='Tangible assets'!O29 -> No | H29: ='Yearly Sales'!O29 -> Yes | I29: ='Investment (capex)'!O29 -> No | J29: ='Wages salaries'!O29 -> Yes | K29: =COUNTIF(F29:J29,"yes") -> 3
A30: =A29+1 -> 29 | B30: IKTK | C30: 42.13 or 16.28 | D30: https://zazatimber.lv/ | E30: - | F30: =Employees!O30 -> Yes | G30: ='Tangible assets'!O30 -> Yes | H30: ='Yearly Sales'!O30 -> Yes | I30: ='Investment (capex)'!O30 -> No | J30: ='Wages salaries'!O30 -> No | K30: =COUNTIF(F30:J30,"yes") -> 3
A31: =A30+1 -> 30 | B31: Scan-Plast Latvia | C31: 22.24 | D31: https://www.scan-plast.com/lv/ | E31: - | F31: =Employees!O31 -> Yes | G31: ='Tangible assets'!O31 -> Yes | H31: ='Yearly Sales'!O31 -> Yes | I31: ='Investment (capex)'!O31 -> Yes | J31: ='Wages salaries'!O31 -> Yes | K31: =COUNTIF(F31:J31,"yes") -> 5
A32: =A31+1 -> 31 | B32: texmex | C32: NA | D32: NA | E32: This is either a type or some scheme idk, also it is the only one granted by the ministry of economics | F32: =Employees!O32 -> No | G32: ='Tangible assets'!O32 -> No | H32: ='Yearly Sales'!O32 -> No | I32: ='Investment (capex)'!O32 -> No | J32: ='Wages salaries'!O32 -> No | K32: =COUNTIF(F32:J32,"yes") -> 0
A33: =A32+1 -> 32 | B33: JELGAVAS TIPOGRĀFIJA | C33: 18.12 | D33: https://jt.lv/en/digital-printing/ | E33: - | F33: =Employees!O33 -> Yes | G33: ='Tangible assets'!O33 -> Yes | H33: ='Yearly Sales'!O33 -> Yes | I33: ='Investment (capex)'!O33 -> Yes | J33: ='Wages salaries'!O33 -> Yes | K33: =COUNTIF(F33:J33,"yes") -> 5
A34: =A33+1 -> 33 | B34: ICS Property | C34: 68.2 | D34: https://www.icsproperty.lv/ | E34: Either someone fucked up the registry or we have texmex publishing company | F34: =Employees!O34 -> No | G34: ='Tangible assets'!O34 -> No | H34: ='Yearly Sales'!O34 -> No | I34: ='Investment (capex)'!O34 -> No | J34: ='Wages salaries'!O34 -> No | K34: =COUNTIF(F34:J34,"yes") -> 0
A35: =A34+1 -> 34 | B35: VIZULO | C35: 27.4 | D35: https://www.vizulo.com/en | F35: =Employees!O35 -> Yes | G35: ='Tangible assets'!O35 -> IDK | H35: ='Yearly Sales'!O35 -> Yes | I35: ='Investment (capex)'!O35 -> Yes | J35: ='Wages salaries'!O35 -> Yes | K35: =COUNTIF(F35:J35,"yes") -> 4
E36: Total | F36: =COUNTIF(F2:F35,"yes") -> 24 | G36: =COUNTIF(G2:G35,"yes") -> 19 | H36: =COUNTIF(H2:H35,"yes") -> 23 | I36: =COUNTIF(I2:I35,"yes") -> 13 | J36: =COUNTIF(J2:J35,"yes") -> 19
I37: Totals | J37: 5 out of 5 | K37: =COUNTIF(K2:K35, "5") -> 11
J38: 4 out of 5 | K38: =COUNTIF(K2:K35, "4") -> 5
J39: 3 out of 5 | K39: =COUNTIF(K2:K35, "3") -> 3
J40: 2 out of 5 | K40: =COUNTIF(K2:K35, "2") -> 6
J41: 1 out of 5 | K41: =COUNTIF(K2:K35, "1") -> 2

Sheet Non treated
A1: Nace code | B1: Name | C1: ID | D1: Notes
A2: 25.4 | B2: AMATEKS | C2: 40003576806
A3: 25.11 | B3: BELMAST | C3: 40003490550
A4: 10.51 | B4: Latvijas maiznieks | C4: 40003034051
A5: 68.2 | B5: LES TRANS | C5: 42103021051
A6: 23.99 | B6: CompositeLine | C6: 40003990979
A7: 20.3 | B7: AS BIOLARS | C7: 40003245470
A8: 25.11 | B8: RK Metāls | C8: 42103009504
A9: 43.22 | B9: VEKTRA-21 | C9: 42103011833
A10: 16.11 | B10: Gaujas Koks | C10: 40003037448
A11: 46.9 | B11: PLUTOS SELL | C11: 40103687559
A12: 19.2 | B12: Baltic new technologies | C12: 41203036919
A13: 41 | B13: AIMASA | C13: 44103032138
... A28: 16.21 | B28: Baltic Block SIA | C28: 40003332918

Sheet Employees
A1: Employees | B1: 2013 | C1: =B1+1 -> 2014 | D1: =C1+1 -> 2015 | E1: =D1+1 -> 2016 | F1: =E1+1 -> 2017 | G1: =F1+1 -> 2018 | H1: =G1+1 -> 2019 | I1: =H1+1 -> 2020 | J1: =I1+1 -> 2021 | ... N1: =M1+1 -> 2025 | O1: DATA FIT | P1: Notes
A2: ='Firm list'!B2 -> Mārupes Metālmeistars | B2: 80 | C2: 80 | D2: 80 | E2: 90 | F2: 96 | G2: 105 | H2: 105 | I2: 115 | J2: 117 | K2: 114 | L2: 75 | M2: 73 | N2: 75 | O2: Yes
A3: ='Firm list'!B3 -> TECNOPALI NORTH EUROPE | B3: 31 | C3: 33 | D3: 38 | E3: 37 | F3: 38 | G3: 44 | H3: 49 | I3: 58 | J3: 61 | K3: 59 | L3: 63 | M3: 63 | N3: NA | O3: Yes
A4: ='Firm list'!B4 -> Ventspils Brīvostas pārvalde | B4: NA | C4: NA | D4: NA | E4: NA | F4: NA | G4: 275 | H4: 269 | I4: 237 | J4: 212 | K4: 185 | L4: 178 | M4: 182 | N4: NA | O4: No
A5: ='Firm list'!B5 -> Tukuma Piens | B5: 245 | C5: 245 | D5: 249 | E5: 217 | F5: 205 | G5: 211 | H5: 209 | I5: 215 | J5: 220 | K5: 192 | L5: 215 | M5: 225 | N5: NA | O5: Yes
A6: ='Firm list'!B6 -> Vecās Ostmalas Biznesa Parks | B6: NA | C6: 0 | D6: 1 | E6: 2 | F6: 5 | G6: 5 | H6: 4 | I6: 4 | J6: 7 | K6: 6 | L6: 6 | M6: 5 | N6: 5 | O6: Yes | S6: T-2 | T6: T-1 | U6: T0 | V6: T1 | W6: T2 | X6: T3
A7: ='Firm list'!B7 -> TRAPI | B7: NA | C7: NA | D7: NA | E7: 0 | F7: 0 | G7: 2 | H7: 2 | I7: 2 | J7: 3 | K7: 3 | L7: 3 | M7: 3 | N7: 3 | O7: No | S7: 80 | T7: 80 | U7: 90 | V7: 96 | W7: 105 | X7: 105 | AF7: =X7-W7 -> 0
A8: ='Firm list'!B8 -> GP TEHNOPARKI | B8: NA | C8: NA | D8: NA | E8: 1 | F8: 5 | G8: 6 | H8: 6 | I8: 1 | J8: 1 | K8: 2 | L8: 2 | M8: 0 | N8: 0 | O8: No | S8: 33 | T8: 38 | U8: 37 | V8: 38 | W8: 44 | X8: 49
A9: ='Firm list'!B9 -> NTC INVESTĪCIJAS | B9: NA | C9: 0 | D9: 0 | E9: 0 | F9: 0 | G9: 0 | H9: 0 | I9: 0 | J9: 0 | K9: 0 | L9: 0 | M9: 1 | N9: 1 | O9: No | P9: Company was only founded in 2014 | S9: 245 | T9: 249 | U9: 217 | V9: 205 | W9: 211 | X9: 209
A10: ='Firm list'!B10 -> TENAX | B10: 18 | C10: 17 | D10: 17 | E10: 7 | F10: 7 | G10: 14 | H10: 15 | I10: 13 | J10: 14 | K10: 14 | L10: 13 | M10: 14 | N10: NA | O10: Yes | S10: 0 | T10: 1 | U10: 2 | V10: 5 | W10: 5 | X10: 4
A11: ='Firm list'!B11 -> IT INTERNATIONAL | B11: 22 | C11: 9 | D11: 8 | E11: 12 | F11: 7 | G11: 1 | H11: NA | I11: NA | J11: NA | K11: NA | L11: NA | M11: NA | N11: NA | O11: No | P11: Liquidated | S11: 17 | T11: 17 | U11: 7 | V11: 7 | W11: 14 | X11: 15
A12: ='Firm list'!B12 -> iCotton | B12: 37 | C12: 64 | D12: 109 | E12: 150 | F12: 149 | G12: 168 | H12: 127 | I12: 111 | J12: 143 | K12: 152 | L12: 158 | M12: 143 | N12: 140 | O12: Yes | S12: 109 | T12: 150 | U12: 149 | V12: 168 | W12: 127 | X12: 111
A13: ='Firm list'!B13 -> Lyngson | B13: 98 | C13: 105 | D13: 108 | E13: 107 | F13: 112 | G13: 133 | H13: 134 | I13: 130 | J13: 128 | K13: 128 | L13: 127 | M13: 114 | N13: NA | O13: Yes | S13: 108 | T13: 107 | U13: 112 | V13: 133 | W13: 134 | X13: 130
A14: ='Firm list'!B14 -> Piebalgas | B14: 79 | C14: 79 | D14: 70 | E14: 68 | F14: 66 | G14: 66 | H14: 63 | I14: 63 | J14: 63 | K14: 62 | L14: 57 | M14: 57 | N14: 56 | O14: Yes | S14: 70 | T14: 68 | U14: 66 | V14: 66 | W14: 63 | X14: 63
A15: ='Firm list'!B15 -> Kronus | B15: NA | C15: 249 | D15: 249 | E15: 249 | F15: 249 | G15: 249 | H15: 356 | I15: 435 | J15: 542 | K15: 538 | L15: 565 | M15: 522 | N15: NA | O15: Yes | S15: 249 | T15: 249 | U15: 249 | V15: 249 | W15: 356 | X15: 435
A16: ='Firm list'!B16 -> NPK Expert | B16: 5 | C16: 33 | D16: 35 | E16: 3 | F16: NA | G16: NA | H16: NA | I16: NA | J16: NA | K16: NA | L16: NA | M16: NA | N16: NA | O16: No | P16: Liquidated | S16: 4 | T16: 2 | U16: 3 | V16: 3 | W16: 4 | X16: 4
A17: ='Firm list'!B17 -> EcoLead | B17: 6 | C17: 6 | D17: 4 | E17: 2 | F17: 3 | G17: 3 | H17: 4 | I17: 4 | J17: 6 | K17: 9 | L17: 34 | M17: 44 | N17: NA | O17: Yes | S17: 3 | T17: 2 | U17: 1 | V17: 1 | W17: 6 | X17: 3
A18: ='Firm list'!B18 -> Carbon energy systems | B18: 1 | C18: 3 | D18: 3 | E18: 2 | F18: 1 | G18: 1 | H18: 6 | I18: 3 | J18: 3 | K18: 1 | L18: 2 | M18: 9 | N18: 10 | O18: Yes | S18: 205 | T18: 221 | U18: 229 | V18: 226 | W18: 243 | X18: 230
A19: ='Firm list'!B19 -> JĒKABPILS PMK | B19: 233 | C19: 260 | D19: 226 | E19: 186 | F19: 205 | G19: 221 | H19: 229 | I19: 226 | J19: 243 | K19: 230 | L19: 236 | M19: 210 | N19: NA | O19: Yes | S19: 67 | T19: 68 | U19: 75 | V19: 71 | W19: 68 | X19: 67
A20: ='Firm list'!B20 -> AmberBirch | B20: NA | C20: NA | D20: NA | E20: NA | F20: 1 | G20: 1 | H20: 14 | I20: 60 | J20: 77 | K20: 83 | L20: 85 | M20: 87 | N20: NA | O20: No | P20: Started operating in 2018 only | S20: 7 | T20: 7 | U20: 6 | V20: 6 | W20: 6 | X20: 6
A21: ='Firm list'!B21 -> VALMIERMUIŽAS ALUS | B21: 30 | C21: 41 | D21: 52 | E21: 63 | F21: 67 | G21: 68 | H21: 75 | I21: 71 | J21: 68 | K21: 67 | L21: 111 | M21: 120 | N21: 127 | O21: Yes | S21: 35 | T21: 60 | U21: 103 | V21: 96 | W21: 103 | X21: 108
A22: ='Firm list'!B22 -> PUMAC LIEPAJA | C22: 10 | D22: 8 | E22: 7 | F22: 7 | G22: 7 | H22: 6 | I22: 6 | J22: 6 | K22: 6 | L22: 6 | M22: 6 | N22: NA | O22: Yes | S22: 82 | T22: 98 | U22: 111 | V22: 104 | W22: 115 | X22: 135
A23: ='Firm list'!B23 -> CEWOOD | B23: 0 | C23: 0 | D23: 2 | E23: 24 | F23: 35 | G23: 60 | H23: 103 | I23: 96 | J23: 103 | K23: 108 | L23: 131 | M23: 155 | N23: NA | O23: Yes | S23: 153 | T23: 174 | U23: 209 | V23: 206 | W23: 213 | X23: 246
A24: ='Firm list'!B24 -> VUDLANDE | B24: 73 | C24: 74 | D24: 74 | E24: 74 | F24: 82 | G24: 98 | H24: 111 | I24: 104 | J24: 115 | K24: 135 | L24: 102 | M24: 108 | N24: 108 | O24: Yes | S24: 78 | T24: 83 | U24: 76 | V24: 73 | W24: 72 | X24: 64
A25: ='Firm list'!B25 -> Artex Latvia | B25: 59 | C25: 70 | D25: 86 | E25: 101 | F25: 153 | G25: 174 | H25: 209 | I25: 206 | J25: 213 | K25: 246 | L25: 277 | M25: 220 | N25: 192 | O25: Yes | S25: 238 | T25: 200 | U25: 222 | V25: 248 | W25: 304 | X25: 350
A26: ='Firm list'!B26 -> SFM Latvia | B26: 30 | C26: 29 | D26: 39 | E26: 52 | F26: 78 | G26: 83 | H26: 76 | I26: 73 | J26: 72 | K26: 64 | L26: 68 | M26: 75 | N26: 95 | O26: Yes | S26: 34 | T26: 57 | U26: 65 | V26: 88 | W26: 112 | X26: 93
A27: ='Firm list'!B27 -> EB Liepāja | B27: NA | C27: NA | D27: NA | E27: NA | F27: NA | G27: 0 | H27: 0 | I27: 0 | J27: 0 | K27: 0 | L27: 0 | M27: 0 | N27: 0 | O27: No | P27: 0 employee company | S27: 14 | T27: 18 | U27: 19 | V27: 24 | W27: 37 | X27: 45
A28: ='Firm list'!B28 -> Stiga RM | B28: 56 | C28: 67 | D28: 141 | E28: 99 | F28: 176 | G28: 238 | H28: 200 | I28: 222 | J28: 248 | K28: 304 | L28: 350 | M28: 409 | N28: NA | O28: Yes | S28: 64 | T28: 58 | U28: 61 | V28: 53 | W28: 52 | X28: 53
A29: ='Firm list'!B29 -> Haugaard Baltic | B29: 0 | C29: 0 | D29: 6 | E29: 12 | F29: 25 | G29: 34 | H29: 57 | I29: 65 | J29: 88 | K29: 112 | L29: 93 | M29: 96 | N29: 114 | O29: Yes | S29: 144 | T29: 163 | U29: 156 | V29: 177 | W29: 198 | X29: 197
A30: ='Firm list'!B30 -> IKTK | B30: 0 | C30: 1 | D30: 4 | E30: 5 | F30: 9 | G30: 14 | H30: 18 | I30: 19 | J30: 24 | K30: 37 | L30: 45 | M30: 49 | N30: 54 | O30: Yes | S30: 99 | T30: 114 | U30: 98 | V30: 117 | W30: 169 | X30: 154 | AB30: T-2 | AC30: T-1 | AD30: T0 | AE30: T1 | AF30: T2 | AG30: T3
A31: ='Firm list'!B31 -> Scan-Plast Latvia | B31: 80 | C31: 68 | D31: 72 | E31: 61 | F31: 63 | G31: 64 | H31: 58 | I31: 61 | J31: 53 | K31: 52 | L31: 53 | M31: 51 | N31: 51 | O31: Yes | R31: Total | S31: =SUM(S7:S30) -> 2138 | T31: =SUM(T7:T30) -> 2284 | U31: =SUM(U7:U30) -> 2363 | V31: =SUM(V7:V30) -> 2460 | W31: =SUM(W7:W30) -> 2761 | X31: =SUM(X7:X30) -> 2876 | AA31: Treated group | AB31: 2138 | AC31: 2284 | AD31: 2363 | AE31: 2460 | AF31: 2761 | AG31: 2876
A32: ='Firm list'!B32 -> texmex | B32: NA | C32: NA | D32: NA | E32: NA | F32: NA | G32: NA | H32: NA | I32: NA | J32: NA | K32: NA | L32: NA | M32: NA | N32: NA | O32: No | AA32: Control group | AB32: 2994 | AC32: 3110 | AD32: 3044 | AE32: 2941 | AF32: 2899 | AG32: 2786
A33: ='Firm list'!B33 -> JELGAVAS TIPOGRĀFIJA | B33: 112 | C33: 111 | D33: 124 | E33: 123 | F33: 129 | G33: 144 | H33: 163 | I33: 156 | J33: 177 | K33: 198 | L33: 197 | M33: 194 | N33: 197 | O33: Yes | AA33: Tr Diff | AE33: =(AE31-AD31)/AD31 -> 0.041049513 | AF33: =(AF31-AD31)/AD31 -> 0.16842996 | AG33: =(AG31-AD31)/AD31 -> 0.21709691
A34: ='Firm list'!B34 -> ICS Property | B34: NA | C34: NA | D34: NA | E34: NA | F34: NA | G34: NA | H34: 2 | I34: 2 | J34: 2 | K34: 2 | L34: 2 | M34: 2 | N34: 2 | O34: No | AA34: Con Diff | AE34: =(AE32-AD32)/AD32 -> -0.033837057 | AF34: =(AF32-AD32)/AD32 -> -0.047634691 | AG34: =(AG32-AD32)/AD32 -> -0.084756899
A35: ='Firm list'!B35 -> VIZULO | B35: 10 | C35: 20 | D35: 44 | E35: 45 | F35: 54 | G35: 73 | H35: 99 | I35: 114 | J35: 98 | K35: 117 | L35: 169 | M35: 154 | N35: NA | O35: Yes | AA35: Diff-in-Diff | AE35: =AE33-AE34 -> 0.07488657 | AF35: =AF33-AF34 -> 0.21606465 | AG35: =AG33-AG34 -> 0.30185381
AA36: Counterfactual treated group | AD36: 2363 | AE36: =AD31+AD31*AE34 -> 2283.043 | AF36: =AD31+AD31*AF34 -> 2250.4392 | AG36: =AD31+AD31*AG34 -> 2162.7194
N37: Total passing | O37: =COUNTIF(O2:O35,"yes") -> 24
A39: Emlpoyees | B39: 2013 | C39: =B39+1 -> 2014 | D39: =C39+1 -> 2015 | E39: =D39+1 -> 2016 | F39: =E39+1 -> 2017 | G39: =F39+1 -> 2018 | H39: =G39+1 -> 2019 | I39: =H39+1 -> 2020 | J39: =I39+1 -> 2021 | ... N39: =M39+1 -> 2025 | O39: DATA FIT | P39: Notes | S39: T-2 | T39: T-1 | U39: T0 | V39: T1 | W39: T2 | X39: T3
A40: BELMAST | C40: 226 | D40: 200 | E40: 168 | F40: 191 | G40: 189 | H40: 165 | S40: 226 | T40: 200 | U40: 168 | V40: 191 | W40: 189 | X40: 165
A41: AMATEKS | C41: 34 | D41: 37 | E41: 46 | F41: 49 | G41: 49 | H41: 43 | S41: 34 | T41: 37 | U41: 46 | V41: 49 | W41: 49 | X41: 43
S42: 249 | T42: 269 | U42: 264 | V42: 252 | W42: 274 | X42: 276
A43: Latvijas maiznieks | C43: 249 | D43: 269 | E43: 264 | F43: 252 | G43: 274 | H43: 276 | S43: 10 | T43: 8 | U43: 8 | V43: 6 | W43: 4 | X43: 5
A44: LES TRANS | C44: 10 | D44: 8 | E44: 8 | F44: 6 | G44: 4 | H44: 5 | S44: 7 | T44: 11 | U44: 14 | V44: 11 | W44: 10 | X44: 13
S45: 199 | T45: 189 | U45: 183 | V45: 175 | W45: 170 | X45: 169
S46: 158 | T46: 171 | U46: 184 | V46: 203 | W46: 214 | X46: 210
S47: 23 | T47: 28 | U47: 28 | V47: 35 | W47: 37 | X47: 34
A48: CompositeLine | C48: 7 | D48: 11 | E48: 14 | F48: 11 | G48: 10 | H48: 13 | S48: 447 | T48: 489 | U48: 433 | V48: 372 | W48: 343 | X48: 357
S49: 3 | T49: 5 | U49: 5 | V49: 6 | W49: 6 | X49: 6
A50: AS BIOLARS | D50: 199 | E50: 189 | F50: 183 | G50: 175 | H50: 170 | I50: 169 | S50: 3 | T50: 5 | U50: 5 | V50: 1 | W50: 1 | X50: 1
A51: RK METALS | D51: 158 | E51: 171 | F51: 184 | G51: 203 | H51: 214 | I51: 210 | S51: 57 | T51: 100 | U51: 116 | V51: 123 | W51: 121 | X51: 103
A52: VEKTRA-21 | D52: 23 | E52: 28 | F52: 28 | G52: 35 | H52: 37 | I52: 34 | S52: 75 | T52: 75 | U52: 75 | V52: 64 | W52: 64 | X52: 61
A53: Gaujas koks | D53: 447 | E53: 489 | F53: 433 | G53: 372 | H53: 343 | I53: 357 | S53: 8 | T53: 3 | U53: 4 | V53: 7 | W53: 19 | X53: 22
S54: 151 | T54: 155 | U54: 161 | V54: 161 | W54: 161 | X54: 144
A55: PLUTOS SELL | D55: 3 | E55: 5 | F55: 5 | G55: 6 | H55: 6 | I55: 6 | S55: 89 | T55: 85 | U55: 78 | V55: 74 | W55: 78 | X55: 76
A56: Baltic new technologies | D56: 3 | E56: 5 | F56: 5 | G56: 1 | H56: 1 | I56: 1 | S56: 446 | T56: 452 | U56: 422 | V56: 384 | W56: 367 | X56: 360
A57: AIMASA | F57: 57 | G57: 100 | H57: 116 | I57: 123 | J57: 121 | K57: 103 | S57: 36 | T57: 39 | U57: 50 | V57: 48 | W57: 51 | X57: 66
H58: 75 | S58: 301 | T58: 296 | U58: 295 | V58: 273 | W58: 263 | X58: 244
A59: Bauskas alus | F59: 75 | G59: 75 | H59: 75 | I59: 64 | J59: 64 | K59: 61 | S59: 86 | T59: 88 | U59: 96 | V59: 106 | W59: 71 | X59: 59
A60: Lion Estate | F60: 8 | G60: 3 | H60: 4 | I60: 7 | J60: 19 | K60: 22 | S60: 33 | T60: 34 | U60: 35 | V60: 38 | W60: 36 | X60: 40
A61: LODE SIA | F61: 151 | G61: 155 | H61: 161 | I61: 161 | J61: 161 | K61: 144 | S61: 64 | T61: 48 | U61: 33 | V61: 31 | W61: 42 | X61: 46
A62: GBM | F62: 89 | G62: 85 | H62: 78 | I62: 74 | J62: 78 | K62: 76 | S62: 271 | T62: 297 | U62: 311 | V62: 300 | W62: 291 | X62: 251
A63: Lauma Fabrics | F63: 446 | G63: 452 | H63: 422 | I63: 384 | J63: 367 | K63: 360 | S63: 18 | T63: 26 | U63: 30 | V63: 31 | W63: 38 | X63: 35
A64: LATSTAB, RSEZ | F64: 36 | G64: 39 | H64: 50 | I64: 48 | J64: 51 | K64: 66 | R64: Total | S64: =SUM(S40:S63) -> 2994 | T64: =SUM(T40:T63) -> 3110 | U64: =SUM(U40:U63) -> 3044 | V64: =SUM(V40:V63) -> 2941 | W64: =SUM(W40:W63) -> 2899 | X64: =SUM(X40:X63) -> 2786
A66: Rettenmeier Baltic Timber | G66: 296 | H66: 295 | I66: 273 | J66: 263 | K66: 244 | L66: 236
A67: HOPPEKIDS | G67: 86 | H67: 88 | I67: 96 | J67: 106 | K67: 71 | L67: 59
A68: Celinieks | G68: 33 | H68: 34 | I68: 35 | J68: 38 | K68: 36 | L68: 40
A69: Immer Digital | G69: 64 | H69: 48 | I69: 33 | J69: 31 | K69: 42 | L69: 46
A71: PNB Print | G71: 271 | H71: 297 | I71: 311 | J71: 300 | K71: 291 | L71: 251
A73: SIA MMG Group | H73: 18 | I73: 26 | J73: 30 | K73: 31 | L73: 38 | M73: 35

Sheet Yearly Sales
A1: Neto apgrozījums | B1: 2013 | C1: =B1+1 -> 2014 | D1: =C1+1 -> 2015 | E1: =D1+1 -> 2016 | F1: =E1+1 -> 2017 | G1: =F1+1 -> 2018 | H1: =G1+1 -> 2019 | I1: =H1+1 -> 2020 | J1: =I1+1 -> 2021 | ... N1: =M1+1 -> 2025 | O1: DATA FIT | P1: Notes
A2: Mārupes Metālmeistars | B2: 5832316 | C2: 5820104 | D2: 6952182 | E2: 7055932 | F2: 9215175 | G2: 9996824 | H2: 11083959 | I2: 10664294 | J2: 15503276 | K2: 16995344 | L2: 11343302 | M2: 9912444 | N2: 9925685 | O2: Yes
A3: TECNOPALI NORTH EUROPE | B3: 1129652 | C3: 2142589 | D3: 3093690 | E3: 2945640 | F3: 3892376 | G3: 5409473 | H3: 5519360 | I3: 6756811 | J3: 8501770 | K3: 13744869 | L3: 11805053 | M3: 9730508 | N3: NA | O3: Yes
A4: Ventspils Brīvostas pārvalde | B4: 17308552 | C4: 24386907 | D4: 21605800 | E4: 20121407 | F4: 21229083 | G4: 21939952 | H4: 23243013 | I4: 15602202 | J4: 15281705 | K4: 19754888 | L4: 15082338 | M4: 17462498 | N4: 18221868 | O4: Yes
A5: Tukuma Piens | B5: 34659059 | C5: 53194916 | D5: 46910324 | E5: 46129720 | F5: 53186134 | G5: 55097643 | H5: 57894764 | I5: 66371774 | J5: 65790286 | K5: 76561185 | L5: 88904649 | M5: 94881767 | N5: NA | O5: Yes
A6: Vecās Ostmalas Biznesa Parks | B6: NA | C6: 0 | D6: 9037 | E6: 145617 | F6: 206622 | G6: 243656 | H6: 370145 | I6: 481693 | J6: 552571 | K6: 742267 | L6: 746750 | M6: 952020 | N6: 946205 | O6: No | P6: Just started this company, might get eschezed results
A7: TRAPI | B7: NA | C7: NA | D7: NA | E7: 0 | F7: 0 | G7: 228115 | H7: 31312 | I7: 10000 | J7: 0 | K7: 114369 | L7: 250422 | M7: 243041 | N7: 243041 | O7: No | S7: T-2 | T7: T-1 | U7: T0 | V7: T1 | W7: T2 | X7: T3
A8: GP TEHNOPARKI | B8: NA | C8: NA | D8: 0 | E8: 0 | F8: 171307 | G8: 325213 | H8: 127025 | I8: 0 | J8: 24439 | K8: 107901 | L8: 74708 | M8: 0 | N8: NA | O8: No | S8: 5820104 | T8: 6952182 | U8: 7055932 | V8: 9215175 | W8: 9996824 | X8: 11083959
A9: NTC INVESTĪCIJAS | B9: 0 | C9: 5573 | D9: 11994 | E9: 24195 | F9: 26928 | G9: 20795 | H9: 33540 | I9: 47925 | J9: 138102 | K9: 197464 | L9: 199946 | M9: 146105 | N9: 282741 | O9: Yes | S9: 2142589 | T9: 3093690 | U9: 2945640 | V9: 3892376 | W9: 5409473 | X9: 5519360
A10: TENAX | B10: 1272814 | C10: 1843543 | D10: 1626775 | E10: 743918 | F10: 829543 | G10: 1053967 | H10: 1641168 | I10: 1694616 | J10: 1879027 | K10: 1953241 | L10: 2289351 | M10: 2523326 | N10: NA | O10: Yes | S10: 24386907 | T10: 21605800 | U10: 20121407 | V10: 21229083 | W10: 21939952 | X10: 23243013
A11: IT INTERNATIONAL | B11: 748487 | C11: 1052571 | D11: 1821154 | E11: 1092818 | F11: 798995 | G11: 226251 | H11: NA | I11: NA | J11: NA | K11: NA | L11: NA | M11: NA | N11: NA | O11: No | P11: Liquidated | S11: 53194916 | T11: 46910324 | U11: 46129720 | V11: 53186134 | W11: 55097643 | X11: 57894764
A12: iCotton | B12: 619128 | C12: 5725894 | D12: 5763079 | E12: 9445222 | F12: 18695782 | G12: 25966495 | H12: 26273886 | I12: 28381032 | J12: 21658350 | K12: 19637448 | L12: 16159823 | M12: 12086459 | N12: 15689933 | O12: Yes | S12: 5573 | T12: 11994 | U12: 24195 | V12: 26928 | W12: 20795 | X12: 33540
A13: Lyngson | B13: 10639668 | C13: 11695598 | D13: 11053920 | E13: 10654491 | F13: 12435811 | G13: 13893616 | H13: 13518423 | I13: 12803242 | J13: 14738615 | K13: 18924058 | L13: 15619301 | M13: 11413608 | N13: NA | O13: Yes | S13: 1843543 | T13: 1626775 | U13: 743918 | V13: 829543 | W13: 1053967 | X13: 1641168
A14: Piebalgas | B14: 6166301 | C14: 7372334 | D14: 5604600 | E14: 5107709 | F14: 6042284 | G14: 6698241 | H14: 5487576 | I14: 6289412 | J14: 7055719 | K14: 9545132 | L14: 6933267 | M14: 7761623 | N14: 5798254 | O14: Yes | S14: 5763079 | T14: 9445222 | U14: 18695782 | V14: 25966495 | W14: 26273886 | X14: 28381032
A15: Kronus | B15: 27201561 | C15: 28035477 | D15: 28124373 | E15: 31388492 | F15: 39978056 | G15: 49109610 | H15: 41317816 | I15: 44435198 | J15: 87752342 | K15: 124736999 | L15: 92892077 | M15: 85969169 | N15: NA | O15: Yes | S15: 11053920 | T15: 10654491 | U15: 12435811 | V15: 13893616 | W15: 13518423 | X15: 12803242
A16: NPK Expert | B16: 2239475 | C16: 10160767 | D16: 15411195 | E16: 14833532 | F16: NA | G16: NA | H16: NA | I16: NA | J16: NA | K16: NA | L16: NA | M16: NA | N16: NA | O16: No | P16: Liquidated | S16: 5604600 | T16: 5107709 | U16: 6042284 | V16: 6698241 | W16: 5487576 | X16: 6289412
A17: EcoLead | B17: NA | C17: NA | D17: NA | E17: NA | F17: NA | G17: NA | H17: NA | I17: NA | J17: 74629 | K17: 180634 | L17: 4101929 | M17: 9777770 | N17: NA | O17: No | S17: 28124373 | T17: 31388492 | U17: 39978056 | V17: 49109610 | W17: 41317816 | X17: 44435198
A18: Carbon energy systems | B18: 0 | C18: 0 | D18: 0 | E18: 0 | F18: 0 | G18: 0 | H18: 0 | I18: 0 | J18: 0 | K18: 0 | L18: 0 | M18: 9040 | N18: 30117 | O18: No | P18: Zero sales | S18: 12483863 | T18: 14667191 | U18: 19698882 | V18: 19101679 | W18: 18073713 | X18: 21877095
A19: JĒKABPILS PMK | B19: 11332031 | C19: 14805701 | D19: 14239816 | E19: 5790706 | F19: 12483863 | G19: 14667191 | H19: 19698882 | I19: 19101679 | J19: 18073713 | K19: 21877095 | L19: 24232828 | M19: 17071487 | N19: NA | O19: Yes | S19: 4605931 | T19: 5372787 | U19: 5683824 | V19: 5517672 | W19: 5816047 | X19: 7016988
A20: AmberBirch | B20: NA | C20: NA | D20: NA | E20: NA | F20: 27907 | G20: 48332 | H20: 220236 | I20: 7420678 | J20: 12397598 | K20: 24001131 | L20: 26626401 | M20: 21647336 | N20: NA | O20: No | S20: 2228728 | T20: 2521113 | U20: 2681245 | V20: 2655026 | W20: 2631479 | X20: 2702046
A21: VALMIERMUIŽAS ALUS | B21: 1751693 | C21: 3387547 | D21: 3840233 | E21: 4226454 | F21: 4605931 | G21: 5372787 | H21: 5683824 | I21: 5517672 | J21: 5816047 | K21: 7016988 | L21: 9435322 | M21: 10018435 | N21: 10538765 | O21: Yes | S21: 1282637 | T21: 4272962 | U21: 6565998 | V21: 7537714 | W21: 10178101 | X21: 12945298
A22: PUMAC LIEPAJA | B22: 1529904 | C22: 1718895 | D22: 1887778 | E22: 2108053 | F22: 2228728 | G22: 2521113 | H22: 2681245 | I22: 2655026 | J22: 2631479 | K22: 2702046 | L22: 3238097 | M22: 3293954 | N22: NA | O22: Yes | S22: 14802416 | T22: 19344872 | U22: 22003118 | V22: 17393548 | W22: 44136749 | X22: 60877228
A23: CEWOOD | B23: 0 | C23: 0 | D23: 0 | E23: 422347 | F23: 1282637 | G23: 4272962 | H23: 6565998 | I23: 7537714 | J23: 10178101 | K23: 12945298 | L23: 14655944 | M23: 16449406 | N23: NA | O23: Yes | S23: 3484504 | T23: 4206259 | U23: 4670600 | V23: 3638136 | W23: 4557049 | X23: 6776697
A24: VUDLANDE | B24: 10689176 | C24: 11691990 | D24: 12760446 | E24: 12979124 | F24: 14802416 | G24: 19344872 | H24: 22003118 | I24: 17393548 | J24: 44136749 | K24: 60877228 | L24: 17603250 | M24: 21696229 | N24: 24291524 | O24: Yes | S24: 6047473 | T24: 5621652 | U24: 5537013 | V24: 5285319 | W24: 6943767 | X24: 10851636
A25: Artex Latvia | B25: 700882 | C25: 869449 | D25: 1396566 | E25: 2366918 | F25: 3484504 | G25: 4206259 | H25: 4670600 | I25: 3638136 | J25: 4557049 | K25: 6776697 | L25: 7428951 | M25: 8217987 | N25: 8632772 | O25: Yes | S25: 24177895 | T25: 20553989 | U25: 23918559 | V25: 43052077 | W25: 69161043 | X25: 76554323
A26: SFM Latvia | B26: 1520335 | C26: 1992739 | D26: 3065305 | E26: 5000487 | F26: 6047473 | G26: 5621652 | H26: 5537013 | I26: 5285319 | J26: 6943767 | K26: 10851636 | L26: 8192943 | M26: 10931159 | N26: 13132882 | O26: Yes | S26: 3097029 | T26: 5661379 | U26: 6427336 | V26: 12636456 | W26: 16456435 | X26: 12265731
A27: EB Liepāja | B27: NA | C27: NA | D27: NA | E27: NA | F27: NA | G27: 0 | H27: 0 | I27: 0 | J27: 0 | K27: 0 | L27: 34000 | M27: 360000 | N27: 360000 | O27: No | S27: 1187395 | T27: 1262077 | U27: 1301518 | V27: 2634776 | W27: 3423393 | X27: 5612526
A28: Stiga RM | B28: 8190870 | C28: 8968714 | D28: 9287255 | E28: 13549693 | F28: 16548536 | G28: 24177895 | H28: 20553989 | I28: 23918559 | J28: 43052077 | K28: 69161043 | L28: 76554323 | M28: 80058988 | N28: NA | O28: Yes | S28: 2737013 | T28: 3215495 | U28: 3688854 | V28: 3060795 | W28: 2762710 | X28: 4663818
A29: Haugaard Baltic | B29: 0 | C29: 0 | D29: 272556 | E29: 898183 | F29: 2008675 | G29: 3097029 | H29: 5661379 | I29: 6427336 | J29: 12636456 | K29: 16456435 | L29: 12265731 | M29: 11584163 | N29: 12967428 | O29: Yes | S29: 11444636 | T29: 11659953 | U29: 10569009 | V29: 14017593 | W29: 17827403 | X29: 17704991
A30: IKTK | B30: 0 | C30: 0 | D30: 486957 | E30: 314743 | F30: 550111 | G30: 1187395 | H30: 1262077 | I30: 1301518 | J30: 2634776 | K30: 3423393 | L30: 5612526 | M30: 5080492 | N30: 5925696 | O30: Yes | S30: 10012999 | T30: 12897734 | U30: 8891546 | V30: 10853349 | W30: 15742864 | X30: 14708042
A31: Scan-Plast Latvia | B31: 0 | C31: 2832111 | D31: 3363649 | E31: 2153098 | F31: 3273100 | G31: 2737013 | H31: 3215495 | I31: 3688854 | J31: 3060795 | K31: 2762710 | L31: 4663818 | M31: 4123429 | N31: 4409458 | O31: Yes
A32: texmex | B32: NA | C32: NA | D32: NA | E32: NA | F32: NA | G32: NA | H32: NA | I32: NA | J32: NA | K32: NA | L32: NA | M32: NA | N32: NA | O32: No | R32: Total | S32: =SUM(S8:S30) -> 235532123 | T32: =SUM(T8:T30) -> 248054142 | U32: =SUM(U8:U30) -> 275810247 | V32: =SUM(V8:V30) -> 331431341 | W32: =SUM(W8:W30) -> 397827108 | X32: =SUM(X8:X30) -> 445881107
A33: JELGAVAS TIPOGRĀFIJA | B33: 5637899 | C33: 7575491 | D33: 8664574 | E33: 9655161 | F33: 9814691 | G33: 11444636 | H33: 11659953 | I33: 10569009 | J33: 14017593 | K33: 17827403 | L33: 17704991 | M33: 17134906 | N33: 18314322 | O33: Yes | AB33: T-2 | AC33: T-1 | AD33: T0 | AE33: T1 | AF33: T2 | AG33: T3
A34: ICS Property | B34: NA | C34: NA | D34: NA | E34: NA | F34: NA | G34: NA | H34: 0 | I34: 0 | J34: 0 | K34: 0 | L34: 0 | M34: 176134 | N34: 176134 | O34: No | AA34: Treated group | AB34: =S32 -> 235532123 | AC34: =T32 -> 248054142 | AD34: =U32 -> 275810247 | AE34: =V32 -> 331431341 | AF34: =W32 -> 397827108 | AG34: =X32 -> 445881107
A35: VIZULO | B35: 199481 | C35: 2860662 | D35: 6069438 | E35: 2556235 | F35: 5503911 | G35: 8062834 | H35: 10012999 | I35: 12897734 | J35: 8891546 | K35: 10853349 | L35: 15742864 | M35: 14708042 | N35: NA | O35: Yes | AA35: Control group | AB35: =S67 -> 290124912 | AC35: =T67 -> 303060311 | AD35: =U67 -> 318995129 | AE35: =V67 -> 362532671 | AF35: =W67 -> 368802682 | AG35: =X67 -> 378379898
AA36: Tr Diff | AE36: =(AE34-AD34)/AD34 -> 0.20166435 | AF36: =(AF34-AD34)/AD34 -> 0.44239423 | AG36: =(AG34-AD34)/AD34 -> 0.6166227
N37: Total passing | O37: =COUNTIF(O2:O35,"yes") -> 23 | AA37: Con Diff | AE37: =(AE35-AD35)/AD35 -> 0.13648341 | AF37: =(AF35-AD35)/AD35 -> 0.15613891 | AG37: =(AG35-AD35)/AD35 -> 0.18616199
AA38: Diff-in-Diff | AE38: =AE36-AE37 -> 0.065180942 | AF38: =AF36-AF37 -> 0.28625531 | AG38: =AG36-AG37 -> 0.43046071
B39: 2013 | C39: =B39+1 -> 2014 | D39: =C39+1 -> 2015 | E39: =D39+1 -> 2016 | F39: =E39+1 -> 2017 | G39: =F39+1 -> 2018 | H39: =G39+1 -> 2019 | I39: =H39+1 -> 2020 | J39: =I39+1 -> 2021 | ... N39: =M39+1 -> 2025 | AA39: Counterfactual treated group | AD39: 275810247 | AE39: =AD34+AD34*AE37 -> 3.1345377e+08 | AF39: =AD34+AD34*AF37 -> 3.1887496e+08 | AG39: =AD34+AD34*AG37 -> 3.2715563e+08
A40: BELMAST | C40: 9179681 | D40: 7353872 | E40: 7786052 | F40: 8995022 | G40: 8351746 | H40: 11643196
A41: AMATEKS | C41: 1271659 | D41: 1810346 | E41: 2632440 | F41: 3023378 | G41: 2512476 | H41: 2369885
A42: Stena Line Ports Liepājas SEZ SIA | C42: 1227344 | D42: 1231817 | E42: 1497862 | F42: 1634470 | G42: 1878101 | H42: 2159992 | S42: T-2 | T42: T-1 | U42: T0 | V42: T1 | W42: T2 | X42: T3
A43: Latvijas maiznieks | C43: 21643930 | D43: 23948682 | E43: 25033375 | F43: 26185754 | G43: 28720476 | H43: 33737121 | S43: 9179681 | T43: 7353872 | U43: 7786052 | V43: 8995022 | W43: 8351746 | X43: 11643196
S44: 1271659 | T44: 1810346 | U44: 2632440 | V44: 3023378 | W44: 2512476 | X44: 2369885
S45: 1227344 | T45: 1231817 | U45: 1497862 | V45: 1634470 | W45: 1878101 | X45: 2159992
S46: 21643930 | T46: 23948682 | U46: 25033375 | V46: 26185754 | W46: 28720476 | X46: 33737121
A47: NP Jelgavas biznesa parks | C47: 1303323 | D47: 1523204 | E47: 2062962 | F47: 2279959 | G47: 2403087 | H47: 2635377 | S47: 1303323 | T47: 1523204 | U47: 2062962 | V47: 2279959 | W47: 2403087 | X47: 2635377
A48: CompositeLine | C48: 323494 | D48: 618092 | E48: 710845 | F48: 409005 | G48: 376180 | H48: 567622 | S48: 323494 | T48: 618092 | U48: 710845 | V48: 409005 | W48: 376180 | X48: 567622
S49: 15300250 | T49: 14971034 | U49: 15332865 | V49: 17589693 | W49: 18045219 | X49: 15170337
A50: AS BIOLARS | D50: 15300250 | E50: 14971034 | F50: 15332865 | G50: 17589693 | H50: 18045219 | I50: 15170337 | S50: 12720505 | T50: 12682480 | U50: 14060953 | V50: 21305276 | W50: 23265077 | X50: 23207254
A51: RK METALS | D51: 12720505 | E51: 12682480 | F51: 14060953 | G51: 21305276 | H51: 23265077 | I51: 23207254 | S51: 568083 | T51: 696888 | U51: 786086 | V51: 1212178 | W51: 1564125 | X51: 1592957
A52: VEKTRA-21 | D52: 568083 | E52: 696888 | F52: 786086 | G52: 1212178 | H52: 1564125 | I52: 1592957 | S52: 59899767 | T52: 65794604 | U52: 60837807 | V52: 82420197 | W52: 66057285 | X52: 76267426
A53: Gaujas koks | D53: 59899767 | E53: 65794604 | F53: 60837807 | G53: 82420197 | H53: 66057285 | I53: 76267426 | S53: 13194079 | T53: 17828939 | U53: 40542567 | V53: 34112185 | W53: 32061744 | X53: 45179988
S54: 5226240 | T54: 7423729 | U54: 7629038 | V54: 6779422 | W54: 6903114 | X54: 7299667
S55: 177766 | T55: 255219 | U55: 535380 | V55: 509156 | W55: 860552 | X55: 243730
S56: 11251624 | T56: 13125057 | U56: 12009005 | V56: 12522057 | W56: 14393708 | X56: 14968605
A57: AIMASA | F57: 13194079 | G57: 17828939 | H57: 40542567 | I57: 34112185 | J57: 32061744 | K57: 45179988 | S57: 3234182 | T57: 3587986 | U57: 3699502 | V57: 3485828 | W57: 4667996 | X57: 5477107
A58: Baltic Block SIA | F58: 12695923 | G58: 17889718 | H58: 19015964 | I58: 18764043 | J58: 29546822 | K58: 44238752 | S58: 32513187 | T58: 31909132 | U58: 32227521 | V58: 24545570 | W58: 29065121 | X58: 31961940
A59: Bauskas alus | F59: 5226240 | G59: 7423729 | H59: 7629038 | I59: 6779422 | J59: 6903114 | K59: 7299667 | S59: 1614744 | T59: 1874312 | U59: 2211178 | V59: 1977373 | W59: 2396100 | X59: 4658940
A60: Lion Estate | F60: 177766 | G60: 255219 | H60: 535380 | I60: 509156 | J60: 860552 | K60: 243730 | S60: 66431261 | T60: 64078285 | U60: 58572768 | V60: 80285744 | W60: 90499158 | X60: 66483710
A61: LODE SIA | F61: 11251624 | G61: 13125057 | H61: 12009005 | I61: 12522057 | J61: 14393708 | K61: 14968605 | S61: 3585452 | T61: 3289652 | U61: 4519585 | V61: 3793563 | W61: 3389772 | X61: 3436003
A62: GBM | F62: 3234182 | G62: 3587986 | H62: 3699502 | I62: 3485828 | J62: 4667996 | K62: 5477107 | S62: 2044223 | T62: 1489434 | U62: 1675623 | V62: 1476762 | W62: 2096159 | X62: 1364420
A63: Lauma Fabrics | F63: 32513187 | G63: 31909132 | H63: 32227521 | I63: 24545570 | J63: 29065121 | K63: 31961940 | S63: 3643016 | T63: 2331137 | U63: 1123166 | V63: 1373632 | W63: 2065920 | X63: 2075301
A64: LATSTAB, RSEZ | F64: 1614744 | G64: 1874312 | H64: 2211178 | I64: 1977373 | J64: 2396100 | K64: 4658940 | S64: 22996221 | T64: 24218653 | U64: 21759842 | V64: 24434167 | W64: 25058580 | X64: 24026891
S65: 774881 | T65: 1017757 | U65: 1748707 | V65: 2182280 | W65: 2170986 | X65: 1852429
A66: Rettenmeier Baltic Timber | G66: 66431261 | H66: 64078285 | I66: 58572768 | J66: 80285744 | K66: 90499158 | L66: 66483710
A67: HOPPEKIDS | G67: 3585452 | H67: 3289652 | I67: 4519585 | J67: 3793563 | K67: 3389772 | L67: 3436003 | R67: Total | S67: =SUM(S43:S65) -> 290124912 | T67: =SUM(T43:T65) -> 303060311 | U67: =SUM(U43:U65) -> 318995129 | V67: =SUM(V43:V65) -> 362532671 | W67: =SUM(W43:W65) -> 368802682 | X67: =SUM(X43:X65) -> 378379898
A68: Celinieks | G68: 2044223 | H68: 1489434 | I68: 1675623 | J68: 1476762 | K68: 2096159 | L68: 1364420
A69: Immer Digital | G69: 3643016 | H69: 2331137 | I69: 1123166 | J69: 1373632 | K69: 2065920 | L69: 2075301
A71: PNB Print | G71: 22996221 | H71: 24218653 | I71: 21759842 | J71: 24434167 | K71: 25058580 | L71: 24026891
A73: SIA MMG Group | H73: 774881 | I73: 1017757 | J73: 1748707 | K73: 2182280 | L73: 2170986 | M73: 1852429

Sheet Investment (capex)
A1: Pamatlīdzekļu un nemateriālo ieguldījumu iegāde | B1: 2013 | C1: =B1+1 -> 2014 | D1: =C1+1 -> 2015 | E1: =D1+1 -> 2016 | F1: =E1+1 -> 2017 | G1: =F1+1 -> 2018 | H1: =G1+1 -> 2019 | I1: =H1+1 -> 2020 | J1: =I1+1 -> 2021 | ... N1: =M1+1 -> 2025 | O1: DATA FIT | P1: Notes
A2: Mārupes Metālmeistars | B2: 208947 | C2: -1204130 | D2: -1866881 | E2: -584561 | F2: -500917 | G2: -428275 | H2: -130080 | I2: -73852 | J2: -528266 | K2: -879762 | L2: -818767 | M2: -525339 | N2: -825026 | O2: Yes
A3: TECNOPALI NORTH EUROPE | B3: -31162 | C3: -302334 | D3: -196678 | E3: NA | F3: NA | G3: NA | H3: -151774 | I3: -318539 | J3: -507376 | K3: -412218 | L3: -398215 | M3: -3506903 | N3: NA | O3: No
A4: Ventspils Brīvostas pārvalde | B4: -19229191 | C4: NA | D4: NA | E4: NA | F4: NA | G4: -20870755 | H4: -21337630 | I4: -6391471 | J4: -3003604 | K4: -3927398 | L4: -9468935 | M4: -3721279 | N4: -2112381 | O4: No
A5: Tukuma Piens | B5: -2836636 | C5: -2178797 | D5: -1603849 | E5: -3198365 | F5: -2602981 | G5: -2305741 | H5: -7235548 | I5: -4747020 | J5: -1039595 | K5: -486127 | L5: -2669876 | M5: -6300366 | N5: NA | O5: Yes
A6: Vecās Ostmalas Biznesa Parks | B6: NA | C6: NA | D6: NA | E6: NA | F6: NA | G6: NA | H6: NA | I6: NA | J6: NA | K6: NA | L6: NA | M6: NA | N6: NA | O6: No | S6: T-2 | T6: T-1 | U6: T0 | V6: T1 | W6: T2 | X6: T3
A7: TRAPI | B7: NA | C7: NA | D7: NA | E7: NA | F7: NA | G7: NA | H7: NA | I7: NA | J7: NA | K7: NA | L7: NA | M7: NA | N7: NA | O7: No | S7: 1204130 | T7: 1866881 | U7: 584561 | V7: 500917 | W7: 428275 | X7: 130080
A8: GP TEHNOPARKI | B8: NA | C8: NA | D8: NA | E8: NA | F8: NA | G8: NA | H8: NA | I8: NA | J8: NA | K8: NA | L8: NA | M8: NA | N8: NA | O8: No | S8: 2178797 | T8: 1603849 | U8: 3198365 | V8: 2602981 | W8: 2305741 | X8: 7235548
A9: NTC INVESTĪCIJAS | B9: NA | C9: NA | D9: NA | E9: NA | F9: NA | G9: NA | H9: NA | I9: NA | J9: NA | K9: NA | L9: NA | M9: NA | N9: NA | O9: No | S9: 8631697 | T9: 668353 | U9: 694074 | V9: 2614693 | W9: 4258609 | X9: 8476925
A10: TENAX | B10: 589920 | C10: -207356 | D10: -610060 | E10: -142271 | F10: -429404 | G10: -609009 | H10: -594680 | I10: -816925 | J10: -83175 | K10: -6423429 | L10: -594803 | M10: -77132 | N10: NA | O10: Yes | S10: 85580 | T10: 1830314 | U10: 1737524 | V10: 1671437 | W10: 470762 | X10: 511136
A11: IT INTERNATIONAL | B11: -53530 | C11: NA | D11: NA | E11: NA | F11: NA | G11: NA | H11: NA | I11: NA | J11: NA | K11: NA | L11: NA | M11: NA | N11: NA | O11: No | P11: Liquidated | S11: 845734 | T11: 2390968 | U11: 2770758 | V11: 1960177 | W11: 1818664 | X11: 706522
A12: iCotton | B12: -1059775 | C12: -202782 | D12: -8631697 | E12: -668353 | F12: -694074 | G12: -2614693 | H12: -4258609 | I12: -8476925 | J12: -5160228 | K12: -1774292 | L12: -1027298 | M12: -284287 | N12: -233604 | O12: Yes | S12: 886122 | T12: 465145 | U12: 926858 | V12: 1695600 | W12: 220385 | X12: 270442
A13: Lyngson | B13: -532832 | C13: -334174 | D13: -85580 | E13: -1830314 | F13: -1737524 | G13: -1671437 | H13: -470762 | I13: -511136 | J13: -334659 | K13: -283242 | L13: -232340 | M13: -317491 | N13: NA | O13: Yes | S13: 615976 | T13: 565719 | U13: 155711 | V13: 115629 | W13: 317090 | X13: 951104
A14: Piebalgas | B14: -170450 | C14: NA | D14: NA | E14: NA | F14: NA | G14: NA | H14: NA | I14: NA | J14: NA | K14: -58223 | L14: -88041 | M14: NA | N14: NA | O14: No | S14: 694254 | T14: 1859123 | U14: 3752044 | V14: 2564153 | W14: 2298728 | X14: 5089609
A15: Kronus | B15: NA | C15: NA | D15: -845734 | E15: -2390968 | F15: -2770758 | G15: -1960177 | H15: -1818664 | I15: -706522 | J15: -1407853 | K15: -4327471 | L15: -3464524 | M15: -804655 | N15: NA | O15: Yes | S15: 9256829 | T15: 6279069 | U15: 11154747 | V15: 4581057 | W15: 19957951 | X15: 28721635
A16: NPK Expert | B16: -32631 | C16: -118259 | D16: NA | E16: NA | F16: NA | G16: NA | H16: NA | I16: NA | J16: NA | K16: NA | L16: NA | M16: NA | N16: NA | O16: No | P16: Liquidated | S16: 36500 | T16: 77762 | U16: 410425 | V16: 214614 | W16: 284027 | X16: 118466
A17: EcoLead | B17: NA | C17: NA | D17: NA | E17: NA | F17: NA | G17: NA | H17: NA | I17: NA | J17: NA | K17: NA | L17: NA | M17: NA | N17: NA | O17: No | S17: 384671 | T17: 796205 | U17: 2311256 | V17: 1205432 | W17: 156125 | X17: 866605
A18: Carbon energy systems | B18: NA | C18: NA | D18: NA | E18: NA | F18: NA | G18: NA | H18: NA | I18: NA | J18: NA | K18: NA | L18: NA | M18: NA | N18: NA | O18: No | S18: 931719 | T18: 889401 | U18: 603234 | V18: 522808 | W18: 2114029 | X18: 2245446
A19: JĒKABPILS PMK | B19: -81165 | C19: -151478 | D19: -68345 | E19: -83611 | F19: -886122 | G19: -465145 | H19: -926858 | I19: -1695600 | J19: -220385 | K19: -270442 | L19: -154089 | M19: -21317 | N19: NA | O19: Yes
A20: AmberBirch | B20: NA | C20: NA | D20: NA | E20: NA | F20: NA | G20: NA | H20: NA | I20: -217435 | J20: -907520 | K20: -710188 | L20: -2827778 | M20: -21591040 | N20: NA | O20: No
A21: VALMIERMUIŽAS ALUS | B21: -559884 | C21: -858128 | D21: -466806 | E21: -299209 | F21: -615976 | G21: -565719 | H21: -155711 | I21: -115629 | J21: -317090 | K21: -951104 | L21: -306655 | M21: -1000400 | N21: -819474 | O21: Yes
A22: PUMAC LIEPAJA | B22: NA | C22: NA | D22: NA | E22: NA | F22: NA | G22: NA | H22: NA | I22: NA | J22: NA | K22: NA | L22: NA | M22: NA | N22: NA | O22: No
A23: CEWOOD | B23: NA | C23: NA | D23: NA | E23: NA | F23: NA | G23: NA | H23: -605614 | I23: -408265 | J23: -1583552 | K23: -7937831 | L23: -4554152 | M23: -5768347 | N23: NA | O23: No
A24: VUDLANDE | B24: NA | C24: -448193 | D24: -446004 | E24: -412864 | F24: -694254 | G24: -1859123 | H24: -3752044 | I24: -2564153 | J24: -2298728 | K24: -5089609 | L24: -6486869 | M24: -6399059 | N24: -3086890 | O24: Yes
A25: Artex Latvia | B25: -2659 | C25: -267955 | D25: -13871 | E25: NA | F25: NA | G25: NA | H25: NA | I25: NA | J25: NA | K25: NA | L25: -201738 | M25: -367817 | N25: -27761 | O25: No
A26: SFM Latvia | B26: -15756 | C26: -2017 | D26: -929301 | E26: NA | F26: NA | G26: NA | H26: NA | I26: NA | J26: NA | K26: -3641942 | L26: -900568 | M26: -1346395 | N26: -1398765 | O26: No
A27: EB Liepāja | B27: NA | C27: NA | D27: NA | E27: NA | F27: NA | G27: NA | H27: NA | I27: NA | J27: NA | K27: NA | L27: NA | M27: NA | N27: NA | O27: No
A28: Stiga RM | B28: -1405376 | C28: -2754322 | D28: -4765085 | E28: -1351776 | F28: -506149 | G28: -9256829 | H28: -6279069 | I28: -11154747 | J28: -4581057 | K28: -19957951 | L28: -28721635 | M28: -36286841 | N28: NA | O28: Yes
A29: Haugaard Baltic | B29: 0 | C29: 0 | D29: -16462 | E29: -39565 | F29: NA | G29: NA | H29: NA | I29: -49774 | J29: -151985 | K29: -108831 | L29: -409519 | M29: -230601 | N29: -428126 | O29: No | AA29: T-2 | AB29: T-1 | AC29: T0 | AD29: T1 | AE29: T2 | AF29: T3
A30: IKTK | B30: NA | C30: NA | D30: NA | E30: NA | F30: NA | G30: NA | H30: NA | I30: NA | J30: NA | K30: NA | L30: NA | M30: NA | N30: NA | O30: No | Z30: Treated group | AA30: =SUM(S7:S18) -> 25752009 | AB30: =SUM(T7:T18) -> 19292789 | AC30: =SUM(U7:U18) -> 28299557 | AD30: =SUM(V7:V18) -> 20249498 | AE30: =SUM(W7:W18) -> 34630386 | AF30: =SUM(X7:X18) -> 55323518
A31: Scan-Plast Latvia | B31: NA | C31: -29131 | D31: -287231 | E31: -65014 | F31: -55968 | G31: -36500 | H31: -77762 | I31: -410425 | J31: -214614 | K31: -284027 | L31: -118466 | M31: -238123 | N31: -118912 | O31: Yes | Z31: Control group | AA31: =SUM(S43:S53) -> 14957102 | AB31: =SUM(T43:T53) -> 16395041 | AC31: =SUM(U43:U53) -> 15613353 | AD31: =SUM(V43:V53) -> 28496274 | AE31: =SUM(W43:W53) -> 37975733 | AF31: =SUM(X43:X53) -> 57077729
A32: texmex | B32: NA | C32: NA | D32: NA | E32: NA | F32: NA | G32: NA | H32: NA | I32: NA | J32: NA | K32: NA | L32: NA | M32: NA | N32: NA | O32: No | Z32: Tr Diff | AD32: =(AD30-$AC$30)/$AC$30 -> -0.28445883 | AE32: =(AE30-$AC$30)/$AC$30 -> 0.22370771 | AF32: =(AF30-$AC$30)/$AC$30 -> 0.95492523
A33: JELGAVAS TIPOGRĀFIJA | B33: -283456 | C33: -2455264 | D33: -453463 | E33: -135721 | F33: -252518 | G33: -384671 | H33: -796205 | I33: -2311256 | J33: -1205432 | K33: -156125 | L33: -866605 | M33: -1097993 | N33: -2258310 | O33: Yes | Z33: Con Diff | AD33: =(AD31-$AC$31)/$AC$31 -> 0.825122 | AE33: =(AE31-$AC$31)/$AC$31 -> 1.4322599 | AF33: =(AF31-$AC$31)/$AC$31 -> 2.6556996
A34: ICS Property | B34: NA | C34: NA | D34: NA | E34: NA | F34: NA | G34: NA | H34: NA | I34: NA | J34: NA | K34: NA | L34: NA | M34: NA | N34: NA | O34: No | Z34: Diff-in-Diff | AD34: =AD32-AD33 -> -1.1095808 | AE34: =AE33-AE32 -> 1.2085522 | AF34: =AF32-AF33 -> -1.7007744
A35: VIZULO | B35: -159830 | C35: -567928 | D35: -398430 | E35: -1036000 | F35: -142797 | G35: -505705 | H35: -931719 | I35: -889401 | J35: -603234 | K35: -522808 | L35: -2114029 | M35: -2245446 | N35: NA | O35: Yes | Z35: Counterfactual treated group | AC35: 28299557 | AD35: =$AC$30+$AC$30*AD33 -> 51650144 | AE35: =$AC$30+$AC$30*AE33 -> 68831879 | AF35: =$AC$30+$AC$30*AF33 -> 1.0345468e+08
N37: Total passing | O37: =COUNTIF(O2:O35,"yes") -> 13
B39: 2013 | C39: =B39+1 -> 2014 | D39: =C39+1 -> 2015 | E39: =D39+1 -> 2016 | F39: =E39+1 -> 2017 | G39: =F39+1 -> 2018 | H39: =G39+1 -> 2019 | I39: =H39+1 -> 2020 | J39: =I39+1 -> 2021 | ... N39: =M39+1 -> 2025
A40: BELMAST | C40: -271472 | D40: -61946 | E40: -117407 | F40: -117481 | G40: -89507 | H40: -50808
S42: T-2 | T42: T-1 | U42: T0 | V42: T1 | W42: T2 | X42: T3
A43: Latvijas maiznieks | C43: -5693692 | D43: -1418863 | E43: -1839087 | F43: -4392493 | G43: -1859065 | H43: -795996 | S43: 271472 | T43: 61946 | U43: 117407 | V43: 117481 | W43: 89507 | X43: 50808
S44: 5693692 | T44: 1418863 | U44: 1839087 | V44: 4392493 | W44: 1859065 | X44: 795996
S45: 262073 | T45: 785129 | U45: 326772 | V45: 165155 | W45: 100511 | X45: 318437
S46: 855985 | T46: 166093 | U46: 236859 | V46: 278814 | W46: 246954 | X46: 303079
S47: 2750614 | T47: 3835203 | U47: 7576674 | V47: 8490818 | W47: 5727820 | X47: 6131561
P48: Replaced CompositeLine | S48: 505948 | T48: 160241 | U48: 139983 | V48: 547913 | W48: 213245 | X48: 780536
S49: 442989 | T49: 36503 | U49: 356782 | V49: 239742 | W49: 150851 | X49: 56286
A50: AS BIOLARS | D50: -262073 | E50: -785129 | F50: -326772 | G50: -165155 | H50: -100511 | I50: -318437 | S50: 15409 | T50: 66453 | U50: 38531 | V50: 121522 | W50: 111061 | X50: 56039
A51: RK METALS | D51: -855985 | E51: -166093 | F51: -236859 | G51: -278814 | H51: -246954 | I51: -303079 | S51: 3603231 | T51: 9019410 | U51: 4465839 | V51: 12963141 | W51: 28255770 | X51: 48187890
S52: 136728 | T52: 430781 | U52: 3810 | V52: 0 | W52: 47282 | X52: 64348
A53: Gaujas koks | D53: -2750614 | E53: -3835203 | F53: -7576674 | G53: -8490818 | H53: -5727820 | I53: -6131561 | S53: 418961 | T53: 414419 | U53: 511609 | V53: 1179195 | W53: 1173667 | X53: 332749
A57: AIMASA | F57: -505948 | G57: -160241 | H57: -139983 | I57: -547913 | J57: -213245 | K57: -780536
A59: Bauskas alus | F59: -442989 | G59: -36503 | H59: -356782 | I59: -239742 | J59: -150851 | K59: -56286
A62: GBM | F62: -15409 | G62: -66453 | H62: -38531 | I62: -121522 | J62: -111061 | K62: -56039
A66: Rettenmeier Baltic Timber | G66: -3603231 | H66: -9019410 | I66: -4465839 | J66: -12963141 | K66: -28255770 | L66: -48187890
A69: ImmerDigital | G69: -136728 | H69: -430781 | I69: -3810 | J69: 0 | K69: -47282 | L69: -64348
A71: PNB Print | G71: -418961 | H71: -414419 | I71: -511609 | J71: -1179195 | K71: -1173667 | L71: -332749
O73: REPLACEMENT NOT FOUND | P73: Replaced SIA MMG Group

Sheet Wages salaries
A1: Wages (with social ins) | B1: 2013 | C1: =B1+1 -> 2014 | D1: =C1+1 -> 2015 | E1: =D1+1 -> 2016 | F1: =E1+1 -> 2017 | G1: =F1+1 -> 2018 | H1: =G1+1 -> 2019 | I1: =H1+1 -> 2020 | J1: =I1+1 -> 2021 | ... N1: =M1+1 -> 2025 | O1: DATA FIT | P1: Notes
A2: Mārupes Metālmeistars | B2: NA | C2: =195281+111944+31759 -> 338984 | D2: =242831+153369+62369 -> 458569 | E2: =234025+54820+64540+15225+161077+37823 -> 567510 | F2: =344521+109074+115954+27356+205246+48136 -> 850287 | G2: =35043+912039+219574 -> 1166656 | H2: =537408+128567+146497+35224+293335+70336+27182 -> 1238549 | I2: =576241+137539+170656+41111+298534+71590 -> 1295671 | J2: =709571+165875+196669+46394+313334+73626 -> 1505469 | K2: =811951+190261+184895+45226+336614+79161 -> 1648108 | L2: =1079737+254034+17367 -> 1351138 | M2: =1110365+260841 -> 1371206 | N2: 1483603 | O2: Yes
A3: TECNOPALI NORTH EUROPE | B3: NA | C3: 523637 | D3: 739499 | E3: 740343 | F3: 813666 | G3: 1058997 | H3: =947783+226319 -> 1174102 | I3: =76431+1187481+285362 -> 1549274 | J3: =65064+1179708+268703 -> 1513475 | K3: =91152+1409148+330171 -> 1830471 | L3: =101399+1746429+410911 -> 2258739 | M3: =83064+1665168+391432 -> 2139664 | N3: NA | O3: Yes
A4: Ventspils Brīvostas pārvalde | B4: NA | C4: NA | D4: NA | E4: NA | F4: NA | G4: 6271518 | H4: 6479286 | I4: 5623563 | J4: 5161503 | K4: 4973708 | L4: 5254175 | M4: =3905879+2168486 -> 6074365 | N4: =2946645+2154938 -> 5101583 | O4: No
A5: Tukuma Piens | B5: NA | C5: =1587240+370757+528210+124434+117748+26398+2225 -> 2757012 | D5: =1672860+391392+583328+160073+119032+27455+2225 -> 2956365 | E5: =1814022+424431+604026+141836+128963+30418+2225 -> 3145921 | F5: =1803781+423116+616694+145136+120395+28457+2225 -> 3139804 | G5: =2234+2713491+649364 -> 3365089 | H5: =2234+3003680+716931 -> 3722845 | I5: =2234+3282168+771092 -> 4055494 | J5: =4820+3473216+810278 -> 4288314 | K5: =7415+3250385+759090 -> 4016890 | L5: =2983262+696604+750409+178772+153465+34410+9195 -> 4806117 | M5: =3228870+755359+803604+188804+161373+36175+10382 -> 5184567 | N5: NA | O5: Yes
A6: Vecās Ostmalas Biznesa Parks | B6: NA | C6: 0 | D6: 2689 | E6: 16095 | F6: 52195 | G6: NA | H6: NA | I6: 58471 | J6: 90409 | K6: 83280 | L6: 85687 | M6: 82899 | N6: 75399 | O6: No | S6: T-2 | T6: T-1 | U6: T0 | V6: T1 | W6: T2 | X6: T3
A7: TRAPI | B7: NA | C7: NA | D7: NA | E7: NA | F7: NA | G7: NA | H7: NA | I7: NA | J7: 2461 | K7: 2545 | L7: 2545 | M7: 4598 | N7: 4598 | O7: No | S7: 523637 | T7: 739499 | U7: 740343 | V7: 813666 | W7: 1058997 | X7: =947783+226319 -> 1174102
A8: GP TEHNOPARKI | B8: NA | C8: NA | D8: NA | E8: =457+107 -> 564 | F8: 36205 | G8: 49309 | H8: NA | I8: NA | J8: NA | K8: NA | L8: NA | M8: NA | N8: NA | O8: No | S8: =1587240+370757+528210+124434+117748+26398+2225 -> 2757012 | T8: =1672860+391392+583328+160073+119032+27455+2225 -> 2956365 | U8: =1814022+424431+604026+141836+128963+30418+2225 -> 3145921 | V8: =1803781+423116+616694+145136+120395+28457+2225 -> 3139804 | W8: =2234+2713491+649364 -> 3365089 | X8: =2234+3003680+716931 -> 3722845
A9: NTC INVESTĪCIJAS | B9: NA | C9: NA | D9: NA | E9: NA | F9: NA | G9: NA | H9: NA | I9: NA | J9: NA | K9: NA | L9: NA | M9: NA | N9: NA | O9: No | S9: =1587240+370757+528210+124434+117748+26398+2225 -> 2757012 | T9: =1672860+391392+583328+160073+119032+27455+2225 -> 2956365 | U9: =1814022+424431+604026+141836+128963+30418+2225 -> 3145921 | V9: =1803781+423116+616694+145136+120395+28457+2225 -> 3139804 | W9: =2234+2713491+649364 -> 3365089 | X9: =2234+3003680+716931 -> 3722845
A10: TENAX | B10: NA | C10: 487571 | D10: 347343 | E10: 347343 | F10: 230115 | G10: =129923+304962+73465 -> 508350 | H10: =95452+393779+94120 -> 583351 | I10: =97915+366201+83002 -> 547118 | J10: =88790+412200+95556 -> 596546 | K10: =108679+662690+154822 -> 926191 | L10: =127603+502595+117477 -> 747675 | M10: =129439+555191+128958 -> 813588 | N10: NA | O10: Yes | S10: 672843 | T10: 1488737 | U10: 2364264 | V10: 2093985 | W10: =1397189+335858 -> 1733047 | X10: =1224695+293551 -> 1518246
A11: IT INTERNATIONAL | B11: NA | C11: =27582+4894 -> 32476 | D11: =42071+5339 -> 47410 | E11: =42071+5339 -> 47410 | F11: =66531+16542 -> 83073 | G11: NA | H11: NA | I11: NA | J11: NA | K11: NA | L11: NA | M11: NA | N11: NA | O11: No | P11: Liquidated | S11: 1567011 | T11: 1599886 | U11: 1800662 | V11: =1823220+440194 -> 2263414 | W11: =1962684+468908 -> 2431592 | X11: =1997755+480731 -> 2478486
A12: iCotton | B12: NA | C12: 653720 | D12: 672843 | E12: 1488737 | F12: 2364264 | G12: 2093985 | H12: =1397189+335858 -> 1733047 | I12: =1224695+293551 -> 1518246 | J12: =1224695+293551 -> 1518246 | K12: =2058606+488562 -> 2547168 | L12: 3092067 | M12: 3093707 | N12: 3128387 | O12: Yes | S12: 53752 | T12: 625967 | U12: 674923 | V12: 784012 | W12: 786842 | X12: 877588
A13: Lyngson | B13: NA | C13: 1444727 | D13: 1567011 | E13: 1599886 | F13: 1800662 | G13: =1823220+440194 -> 2263414 | H13: =1962684+468908 -> 2431592 | I13: =1997755+480731 -> 2478486 | J13: =2065905+494962 -> 2560867 | K13: =2342510+557518 -> 2900028 | L13: =2397093+553827 -> 2950920 | M13: =2306816+544716 -> 2851532 | N13: NA | O13: Yes | S13: =1606020+524470 -> 2130490 | T13: =1838130+563434 -> 2401564 | U13: =2372147+804324+716872 -> 3893343 | V13: =2813174+109163+1499409 -> 4421746 | W13: =5707479+362808+1983536 -> 8053823 | X13: =7114531+207880+3154228 -> 10476639
A14: Piebalgas | B14: NA | C14: 53860 | D14: 53752 | E14: 625967 | F14: 674923 | G14: 784012 | H14: 786842 | I14: 877588 | J14: 919445 | K14: 1050025 | L14: 1067345 | M14: 1085866 | N14: 1090279 | O14: Yes | S14: =2161442+502057+265722+61557 -> 2990778 | T14: =2488010+594594+316042+75529 -> 3474175 | U14: =2846906+679946+366826+87612 -> 3981290 | V14: =2966961+708413+439671+104979 -> 4220024 | W14: =2866683+670662+471396+110456 -> 4119197 | X14: =3097929+721680+465735+108496 -> 4393840
A15: Kronus | B15: =1435632+431371 -> 1867003 | C15: =1464702+462987 -> 1927689 | D15: =1606020+524470 -> 2130490 | E15: =1838130+563434 -> 2401564 | F15: =2372147+804324+716872 -> 3893343 | G15: =2813174+109163+1499409 -> 4421746 | H15: =5707479+362808+1983536 -> 8053823 | I15: =7114531+207880+3154228 -> 10476639 | J15: =8094944+233446+4373458 -> 12701848 | K15: =11970474+360909+4303150 -> 16634533 | L15: =10803022+268791+5952190 -> 17024003 | M15: =9792677+185160+6063677 -> 16041514 | N15: NA | O15: Yes | S15: 897858 | T15: =803020+193021 -> 996041 | U15: =563511+135822+324573+77739+111528+26857 -> 1240030 | V15: =534041+128594+307771+73942+155958+37462 -> 1237768 | W15: =628521+148309+336495+79338+189410+33672 -> 1415745 | X15: =630531+140783+380093+89276+208465+47283 -> 1496431
A16: NPK Expert | B16: NA | C16: NA | D16: =392052 -> 392052 | E16: =342653 -> 342653 | F16: NA | G16: NA | H16: NA | I16: NA | J16: NA | K16: NA | L16: NA | M16: NA | N16: NA | O16: No | P16: Liquidated | S16: =653969+154222+187202+44148 -> 1039541 | T16: =860638+204993+169798+40504 -> 1275933 | U16: =1050270+252907+170+41045 -> 1344392 | V16: =36482+1242585+298875 -> 1577942 | W16: =26400+1593403+385272 -> 2005075 | X16: =26400+1879954+448670 -> 2355024
A17: EcoLead | B17: 52387 | C17: 48881 | D17: =31453+6355 -> 37808 | E17: NA | F17: NA | G17: NA | H17: NA | I17: NA | J17: =42902 -> 42902 | K17: =88791 -> 88791 | L17: =640601+312476 -> 953077 | M17: =1366179+375053 -> 1741232 | N17: NA | O17: No | S17: 1336475 | T17: 1539649 | U17: =1523044+365845 -> 1888889 | V17: =1459061+350323 -> 1809384 | W17: =1717374+403744 -> 2121118 | X17: =2114669+497498 -> 2612167
A18: Carbon energy systems | B18: NA | C18: NA | D18: NA | E18: NA | F18: NA | G18: NA | H18: NA | I18: NA | J18: NA | K18: NA | L18: NA | M18: NA | N18: NA | O18: No | S18: =6000+3087487+743739 -> 3837226 | T18: =6000+2592941+623879 -> 3222820 | U18: =13748+3118584+748305 -> 3880637 | V18: =14427+3865496+909364 -> 4789287 | W18: =14315+5508734+1299635 -> 6822684 | X18: =7576995+1784122 -> 9361117
A19: JĒKABPILS PMK | B19: NA | C19: NA | D19: =2029415+478320+279134+65095 -> 2851964 | E19: =260026+60589+1613220+381025 -> 2314860 | F19: =2161442+502057+265722+61557 -> 2990778 | G19: =2488010+594594+316042+75529 -> 3474175 | H19: =2846906+679946+366826+87612 -> 3981290 | I19: =2966961+708413+439671+104979 -> 4220024 | J19: =2866683+670662+471396+110456 -> 4119197 | K19: =3097929+721680+465735+108496 -> 4393840 | L19: =4694489 -> 4694489 | M19: =4424782 -> 4424782 | N19: NA | O19: Yes | S19: =403680+70217 -> 473897 | T19: =1043122+195260 -> 1238382 | U19: =1142937+366211 -> 1509148 | V19: =108146+1688995+400414 -> 2197555 | W19: =2341242+576736 -> 2917978 | X19: =567976+1962048 -> 2530024
A20: AmberBirch | B20: NA | C20: NA | D20: NA | E20: NA | F20: 11962 | G20: =36679 -> 36679 | H20: =114204+0+127096 -> 241300 | I20: =1011232+25404+102308 -> 1138944 | J20: 1482843 | K20: 2071993 | L20: 2547673 | M20: 3185787 | N20: NA | O20: Yes | S20: =27073+702952+169619+279 -> 899923 | T20: =27061+737702+177714+252 -> 942729 | U20: 957362 | V20: 913335 | W20: 943043 | X20: 1017789
A21: VALMIERMUIŽAS ALUS | B21: NA | C21: 368029 | D21: 1139550 | E21: 758006 | F21: 897858 | G21: =803020+193021 -> 996041 | H21: =563511+135822+324573+77739+111528+26857 -> 1240030 | I21: =534041+128594+307771+73942+155958+37462 -> 1237768 | J21: =628521+148309+336495+79338+189410+33672 -> 1415745 | K21: =630531+140783+380093+89276+208465+47283 -> 1496431 | L21: =695725+164380+927205+218637+275941+65079 -> 2346967 | M21: =1106030+262444+271499+64127+718717+169569 -> 2592386 | N21: =956223+225607+1193245+280479+364653+85996 -> 3106203 | O21: Yes | S21: =139952+2349744 -> 2489696 | T21: =182229+3168821 -> 3351050 | U21: =126285+2714085 -> 2840370 | V21: =114182+2927828+687498 -> 3729508 | W21: =77905+3369880+792513 -> 4240298 | X21: =87136+3682417+866835 -> 4636388
A22: PUMAC LIEPAJA | B22: NA | C22: 75037 | D22: 81948 | E22: 74668 | F22: 73717 | G22: 77664 | H22: 74141 | I22: 81011 | J22: 87401 | K22: 88992 | L22: 95116 | M22: 117357 | N22: NA | O22: Yes | S22: =46925+1195585+287677 -> 1530187 | T22: =85902+1232223+293922 -> 1612047 | U22: =33548+1149732+271180 -> 1454460 | V22: =37076+1461207+344669 -> 1842952 | W22: =26318+1964535+462485 -> 2453338 | X22: =26315+2227947+526641 -> 2780903
A23: CEWOOD | B23: NA | C23: NA | D23: NA | E23: NA | F23: NA | G23: =762270+111476+24456 -> 898202 | H23: NA | I23: 1367960 | J23: 1673246 | K23: 1962707 | L23: 2563557 | M23: 3300140 | N23: NA | O23: No | R23: Total | S23: =SUM(S7:S22) -> 25957338 | T23: =SUM(T7:T22) -> 30421209 | U23: =SUM(U7:U22) -> 34861955 | V23: =SUM(V7:V22) -> 38974186 | W23: =SUM(W7:W22) -> 47832955 | X23: =SUM(X7:X22) -> 55154434
A24: VUDLANDE | B24: NA | C24: =106346+25313+383691+91430 -> 606780 | D24: =420087+99026+148912+34240 -> 702265 | E24: =523381+123249+141457+33357 -> 821444 | F24: =653969+154222+187202+44148 -> 1039541 | G24: =860638+204993+169798+40504 -> 1275933 | H24: =1050270+252907+170+41045 -> 1344392 | I24: =36482+1242585+298875 -> 1577942 | J24: =26400+1593403+385272 -> 2005075 | K24: =26400+1879954+448670 -> 2355024 | L24: =26510+1353008+318254 -> 1697772 | M24: =26384+1539447+361806 -> 1927637 | N24: =26400+1645508+388069 -> 2059977 | O24: Yes
A25: Artex Latvia | B25: NA | C25: =299974+70729+130432+10889+30447+2890 -> 545361 | D25: =388047+91417+151671+20448+35224+5277 -> 692084 | E25: 845867 | F25: 1336475 | G25: 1539649 | H25: =1523044+365845 -> 1888889 | I25: =1459061+350323 -> 1809384 | J25: =1717374+403744 -> 2121118 | K25: =2114669+497498 -> 2612167 | L25: =2657297+625375 -> 3282672 | M25: =2413777+560673 -> 2974450 | N25: =2412096+560276 -> 2972372 | O25: Yes
A26: SFM Latvia | B26: NA | C26: =121613+28642 -> 150255 | D26: =177409+41688+8837+928 -> 228862 | E26: =611650+119652 -> 731302 | F26: NA | G26: =879303+213273+264332+61378 -> 1418286 | H26: =787171+188486+329271+79103 -> 1384031 | I26: =879611+554142 -> 1433753 | J26: =747339+666762 -> 1414101 | K26: =619457+774174 -> 1393631 | L26: =693024+936158 -> 1629182 | M26: =1254478+1055501 -> 2309979 | N26: =1964834+1260971 -> 3225805 | O26: No
A27: EB Liepāja | B27: NA | C27: NA | D27: NA | E27: NA | F27: NA | G27: 0 | H27: 0 | I27: 0 | J27: 0 | K27: 0 | L27: 0 | M27: 0 | N27: 0 | O27: No | Z27: Wage per person
A28: Stiga RM | B28: NA | C28: 627283 | D28: 1013675 | E28: =930832+189095 -> 1119927 | F28: =2040625+189759 -> 2230384 | G28: =6000+3087487+743739 -> 3837226 | H28: =6000+2592941+623879 -> 3222820 | I28: =13748+3118584+748305 -> 3880637 | J28: =14427+3865496+909364 -> 4789287 | K28: =14315+5508734+1299635 -> 6822684 | L28: =7576995+1784122 -> 9361117 | M28: =9266004+2183130 -> 11449134 | N28: NA | O28: Yes | AA28: T-2 | AB28: T-1 | AC28: T0 | AD28: T1 | AE28: T2 | AF28: T3
A29: Haugaard Baltic | B29: NA | C29: NA | D29: =64905+3694 -> 68599 | E29: =177033+18421 -> 195454 | F29: =161893+20886 -> 182779 | G29: =403680+70217 -> 473897 | H29: =1043122+195260 -> 1238382 | I29: =1142937+366211 -> 1509148 | J29: =108146+1688995+400414 -> 2197555 | K29: =2341242+576736 -> 2917978 | L29: =567976+1962048 -> 2530024 | M29: =1711692+403792+561761+132519 -> 2809764 | N29: =1999924+472390+759748+179150 -> 3411212 | O29: Yes | Z29: Treated group | AA29: =S23/Employees!S31 -> 12140.944 | AB29: =T23/Employees!T31 -> 13319.268 | AC29: =U23/Employees!U31 -> 14753.261 | AD29: =V23/Employees!V31 -> 15843.165 | AE29: =W23/Employees!W31 -> 17324.504 | AF29: =X23/Employees!X31 -> 19177.481
A30: IKTK | B30: NA | C30: NA | D30: NA | E30: NA | F30: NA | G30: NA | H30: NA | I30: NA | J30: NA | K30: NA | L30: NA | M30: NA | N30: NA | O30: No | Z30: Control group | AA30: =S56/Employees!S64 -> 12228.492 | AB30: =T56/Employees!T64 -> 13212.327 | AC30: =U56/Employees!U64 -> 13273.681 | AD30: =V56/Employees!V64 -> 14230.376 | AE30: =W56/Employees!W64 -> 15265.882 | AF30: =X56/Employees!X64 -> 16251.615
A31: Scan-Plast Latvia | B31: NA | C31: =432092+101663+56301+238664 -> 828720 | D31: =504884+119102+208000+48807 -> 880793 | E31: NA | F31: NA | G31: =27073+702952+169619+279 -> 899923 | H31: =27061+737702+177714+252 -> 942729 | I31: 957362 | J31: 913335 | K31: 943043 | L31: 1017789 | M31: 1058653 | N31: 1342013 | O31: Yes | Z31: Tr Diff | AD31: =(AD29-$AC$29)/$AC$29 -> 0.07387549 | AE31: =(AE29-$AC$29)/$AC$29 -> 0.17428304 | AF31: =(AF29-$AC$29)/$AC$29 -> 0.29988082
A32: texmex | B32: NA | C32: NA | D32: NA | E32: NA | F32: NA | G32: NA | H32: NA | I32: NA | J32: NA | K32: NA | L32: NA | M32: NA | N32: NA | O32: No | Z32: Con Diff | AD32: =(AD30-$AC$30)/$AC$30 -> 0.072074586 | AE32: =(AE30-$AC$30)/$AC$30 -> 0.15008661 | AF32: =(AF30-$AC$30)/$AC$30 -> 0.22434879
A33: JELGAVAS TIPOGRĀFIJA | B33: NA | C33: =1725234+96113 -> 1821347 | D33: =2052134+125401 -> 2177535 | E33: =67418+2208828 -> 2276246 | F33: =77060+2363595 -> 2440655 | G33: =139952+2349744 -> 2489696 | H33: =182229+3168821 -> 3351050 | I33: =126285+2714085 -> 2840370 | J33: =114182+2927828+687498 -> 3729508 | K33: =77905+3369880+792513 -> 4240298 | L33: =87136+3682417+866835 -> 4636388 | M33: =85026+3952635+930996 -> 4968657 | N33: =96381+4067995+937485 -> 5101861 | O33: Yes | Z33: Diff-in-Diff | AD33: =AD31-AD32 -> 0.0018009036 | AE33: =AE31-AE32 -> 0.024196433 | AF33: =AF31-AF32 -> 0.075532027
A34: ICS Property | B34: NA | C34: NA | D34: NA | E34: NA | F34: NA | G34: NA | H34: NA | I34: NA | J34: NA | K34: NA | L34: NA | M34: NA | N34: NA | O34: No | Z34: Counterfactual treated group | AC34: 14753.261 | AD34: =$AC$29+$AC$29*AD32 -> 15816.596 | AE34: =$AC$29+$AC$29*AE32 -> 16967.528 | AF34: =$AC$29+$AC$29*AF32 -> 18063.137
A35: VIZULO | B35: NA | C35: =61985 -> 61985 | D35: =173955 -> 173955 | E35: =405370+7974 -> 413344 | F35: =12638+647193 -> 659831 | G35: =16550+889982+214396 -> 1120928 | H35: =46925+1195585+287677 -> 1530187 | I35: =85902+1232223+293922 -> 1612047 | J35: =33548+1149732+271180 -> 1454460 | K35: =37076+1461207+344669 -> 1842952 | L35: =26318+1964535+462485 -> 2453338 | M35: =26315+2227947+526641 -> 2780903 | N35: NA | O35: Yes
N37: Total passing | O37: =COUNTIF(O2:O35,"yes") -> 19
B39: 2013 | C39: =B39+1 -> 2014 | D39: =C39+1 -> 2015 | E39: =D39+1 -> 2016 | F39: =E39+1 -> 2017 | G39: =F39+1 -> 2018 | H39: =G39+1 -> 2019 | I39: =H39+1 -> 2020 | J39: =I39+1 -> 2021 | ... N39: =M39+1 -> 2025
O40: Yes | S40: T-2 | T40: T-1 | U40: T0 | V40: T1 | W40: T2 | X40: T3
A41: AMATEKS | C41: 752795 | D41: 633915 | E41: 752795 | F41: 803196 | G41: 939876 | H41: 860881 | O41: Yes | S41: 752795 | T41: 633915 | U41: 752795 | V41: 803196 | W41: 939876 | X41: 860881
O42: No | S42: 2651779 | T42: 2869174 | U42: 2932364 | V42: 3011009 | W42: 3447944 | X42: 3829802
A43: Latvijas maiznieks | C43: 2651779 | D43: 2869174 | E43: 2932364 | F43: 3011009 | G43: 3447944 | H43: 3829802 | O43: Yes | S43: 2640313 | T43: 2493458 | U43: 2471892 | V43: 2506788 | W43: 2662196 | X43: 2809893
O44: No | S44: 3380544 | T44: 3889697 | U44: 4174625 | V44: 5252771 | W44: 5549549 | X44: 5501939
O45: No | S45: 181047 | T45: 177670 | U45: 207522 | V45: 316117 | W45: 388059 | X45: 330253
O46: No | S46: 6513403 | T46: 7852348 | U46: 6707053 | V46: 6853377 | W46: 6135853 | X46: 6943181
O47: No | S47: 554860 | T47: 1118711 | U47: 1725553 | V47: 1835619 | W47: 1998244 | X47: 1901184
O48: Yes | S48: 1163468 | T48: 1387079 | U48: 1398071 | V48: 1202447 | W48: 1107705 | X48: 1126972
O49: No | S49: 824543 | T49: 802150 | U49: 797539 | V49: 880978 | W49: 1044989 | X49: 1250507
A50: AS BIOLARS | D50: 2640313 | E50: 2493458 | F50: 2471892 | G50: 2506788 | H50: 2662196 | I50: 2809893 | O50: Yes | S50: 5363077 | T50: 5514364 | U50: 5509360 | V50: 4892276 | W50: 6458716 | X50: 6152159
A51: RK METALS | D51: 3380544 | E51: 3889697 | F51: 4174625 | G51: 5252771 | H51: 5549549 | I51: 5501939 | O51: Yes | S51: 5811448 | T51: 5854072 | U51: 5956452 | V51: 5903016 | W51: 5962837 | X51: 5976099
A52: VEKTRA-21 | D52: 181047 | E52: 177670 | F52: 207522 | G52: 316117 | H52: 388059 | I52: 330253 | O52: Yes | S52: =229236+718243+40643 -> 988122 | T52: =240718+724752+40579 -> 1006049 | U52: =883123+283429+43198 -> 1209750 | V52: =920719+288877+26136 -> 1235732 | W52: =957046+271164+18626 -> 1246836 | X52: =851014+263628+21289 -> 1135931
A53: Gaujas koks | D53: 6513403 | E53: 7852348 | F53: 6707053 | G53: 6853377 | H53: 6135853 | I53: 6943181 | O53: Yes | S53: 1216541 | T53: 1178964 | U53: 686952 | V53: 583198 | W53: 755461 | X53: 841730
O54: No | S54: =60439+4451321 -> 4511760 | T54: =4992147+1188535 -> 6180682 | U54: =4594894+1101969 -> 5696863 | V54: =5168357+1209100 -> 6377457 | W54: =4985607+1174075 -> 6159682 | X54: =5032586+1187256 -> 6219842
O55: No | S55: =30014+7230+17054+4108 -> 58406 | T55: =40824+9832+65555+15792 -> 132003 | U55: =144285+34008 -> 178293 | V55: 197554 | W55: 397846 | X55: 396626
O56: No | R56: Total | S56: =SUM(S41:S55) -> 36612106 | T56: =SUM(T41:T55) -> 41090336 | U56: =SUM(U41:U55) -> 40405084 | V56: =SUM(V41:V55) -> 41851535 | W56: =SUM(W41:W55) -> 44255793 | X56: =SUM(X41:X55) -> 45276999
A57: AIMASA | F57: 554860 | G57: 1118711 | H57: 1725553 | I57: 1835619 | J57: 1998244 | K57: 1901184 | O57: Yes
O58: Yes
A59: Bauskas alus | F59: 1163468 | G59: 1387079 | H59: 1398071 | I59: 1202447 | J59: 1107705 | K59: 1126972 | O59: Yes
O60: Yes | P60: Replaed Lion Estate
O61: No
A62: GBM | F62: 824543 | G62: 802150 | H62: 797539 | I62: 880978 | J62: 1044989 | K62: 1250507 | O62: Yes
A63: Lauma Fabrics | F63: 5363077 | G63: 5514364 | H63: 5509360 | I63: 4892276 | J63: 6458716 | K63: 6152159 | O63: Yes
O64: No
O65: No
A66: Rettenmeier Baltic Timber | G66: 5811448 | H66: 5854072 | I66: 5956452 | J66: 5903016 | K66: 5962837 | L66: 5976099 | O66: Yes
A67: HOPPEKIDS | G67: =229236+718243+40643 -> 988122 | H67: =240718+724752+40579 -> 1006049 | I67: =883123+283429+43198 -> 1209750 | J67: =920719+288877+26136 -> 1235732 | K67: =957046+271164+18626 -> 1246836 | L67: =851014+263628+21289 -> 1135931 | O67: Yes
O68: No
A69: Immer Digital | G69: 1216541 | H69: 1178964 | I69: 686952 | J69: 583198 | K69: 755461 | L69: 841730 | O69: Yes
O70: No
A71: PNB Print | G71: =60439+4451321 -> 4511760 | H71: =4992147+1188535 -> 6180682 | I71: =4594894+1101969 -> 5696863 | J71: =5168357+1209100 -> 6377457 | K71: =4985607+1174075 -> 6159682 | L71: =5032586+1187256 -> 6219842 | O71: Yes
O72: No
A73: SIA MMG Group | H73: =30014+7230+17054+4108 -> 58406 | I73: =40824+9832+65555+15792 -> 132003 | J73: =144285+34008 -> 178293 | K73: 197554 | L73: 397846 | M73: 396626 | O73: Yes

Sheet Reversed sheets
A1: Employment | S1: Investment | AK1: Sales | BC1: Wages
A3: Employees | B3: 2025 | C3: 2024 | D3: =C3-1 -> 2023 | E3: =D3-1 -> 2022 | F3: =E3-1 -> 2021 | G3: =F3-1 -> 2020 | H3: =G3-1 -> 2019 | I3: =H3-1 -> 2018 | J3: =I3-1 -> 2017 | K3: =J3-1 -> 2016 | ... N3: =M3-1 -> 2013 | O3: DATA FIT | P3: Notes | S3: Pamatlīdzekļu un nemateriālo ieguldījumu iegāde | T3: 2025 | U3: 2024 | V3: 2023 | W3: 2022 | X3: 2021 | Y3: 2020 | Z3: 2019 | AA3: 2018 | AB3: 2017 | AC3: 2016 | AD3: 2015 | AE3: 2014 | AF3: 2013 | AG3: DATA FIT | AH3: Notes | AK3: Neto apgrozījums | AL3: 2025 | AM3: 2024 | AN3: 2023 | AO3: 2022 | AP3: 2021 | AQ3: 2020 | AR3: 2019 | AS3: 2018 | AT3: 2017 | AU3: 2016 | AV3: 2015 | AW3: 2014 | AX3: 2013 | AY3: DATA FIT | AZ3: Notes | BC3: Wages (with social ins) | BD3: 2025 | BE3: 2024 | BF3: 2023 | BG3: 2022 | BH3: 2021 | BI3: 2020 | BJ3: 2019 | BK3: 2018 | BL3: 2017 | BM3: 2016 | BN3: 2015 | BO3: 2014 | BP3: 2013 | BQ3: DATA FIT | BR3: Notes
A4: ='Firm list'!B4 -> Ventspils Brīvostas pārvalde | B4: 75 | C4: 73 | D4: 75 | E4: 114 | F4: 117 | G4: 115 | H4: 105 | I4: 105 | J4: 96 | K4: 90 | L4: 80 | M4: 80 | N4: 80 | O4: Yes | S4: Mārupes Metālmeistars | T4: -825026 | U4: -525339 | V4: -818767 | W4: -879762 | X4: -528266 | Y4: -73852 | Z4: -130080 | AA4: -428275 | AB4: -500917 | AC4: -584561 | AD4: -1866881 | AE4: -1204130 | AF4: 208947 | AG4: Yes | AK4: Mārupes Metālmeistars | AL4: 9925685 | AM4: 9912444 | AN4: 11343302 | AO4: 16995344 | AP4: 15503276 | AQ4: 10664294 | AR4: 11083959 | AS4: 9996824 | AT4: 9215175 | AU4: 7055932 | AV4: 6952182 | AW4: 5820104 | AX4: 5832316 | AY4: Yes | BC4: Mārupes Metālmeistars | BD4: 1483603 | BE4: 1371206 | BF4: 1351138 | BG4: 1648108 | BH4: 1505469 | BI4: 1295671 | BJ4: 1238549 | BK4: 1166656 | BL4: 850287 | BM4: 567510 | BN4: 458569 | BO4: 338984 | BP4: NA | BQ4: Yes
A5: ='Firm list'!B5 -> Tukuma Piens | B5: NA | C5: 63 | D5: 63 | E5: 59 | F5: 61 | G5: 58 | H5: 49 | I5: 44 | J5: 38 | K5: 37 | L5: 38 | M5: 33 | N5: 31 | O5: Yes | S5: TECNOPALI NORTH EUROPE | T5: NA | U5: -3506903 | V5: -398215 | W5: -412218 | X5: -507376 | Y5: -318539 | Z5: -151774 | AA5: NA | AB5: NA | AC5: NA | AD5: -196678 | AE5: -302334 | AF5: -31162 | AG5: No | AK5: TECNOPALI NORTH EUROPE | AL5: NA | AM5: 9730508 | AN5: 11805053 | AO5: 13744869 | AP5: 8501770 | AQ5: 6756811 | AR5: 5519360 | AS5: 5409473 | AT5: 5409473 | AU5: 2945640 | AV5: 3093690 | AW5: 2142589 | AX5: 1129652 | AY5: Yes | BC5: TECNOPALI NORTH EUROPE | BD5: NA | BE5: 2139664 | BF5: 2258739 | BG5: 1830471 | BH5: 1513475 | BI5: 1549274 | BJ5: 1174102 | BK5: 1058997 | BL5: 813666 | BM5: 740343 | BN5: 739499 | BO5: 523637 | BP5: NA | BQ5: Yes
A6: ='Firm list'!B6 -> Vecās Ostmalas Biznesa Parks | B6: NA | C6: 182 | D6: 178 | E6: 185 | F6: 212 | G6: 237 | H6: 269 | I6: 275 | J6: NA | K6: NA | L6: NA | M6: NA | N6: NA | O6: No | S6: Ventspils Brīvostas pārvalde | T6: -2112381 | U6: -3721279 | V6: -9468935 | W6: -3927398 | X6: -3003604 | Y6: -6391471 | Z6: -21337630 | AA6: -20870755 | AB6: NA | AC6: NA | AD6: NA | AE6: NA | AF6: -19229191 | AG6: No | AK6: Ventspils Brīvostas pārvalde | AL6: 18221868 | AM6: 17462498 | AN6: 15082338 | AO6: 19754888 | AP6: 15281705 | AQ6: 15602202 | AR6: 23243013 | AS6: 21939952 | AT6: 21229083 | AU6: 20121407 | AV6: 21605800 | AW6: 24386907 | AX6: 17308552 | AY6: Yes | BC6: Ventspils Brīvostas pārvalde | BD6: 5101583 | BE6: 6074365 | BF6: 5254175 | BG6: 4973708 | BH6: 5161503 | BI6: 5623563 | BJ6: 6479286 | BK6: 6271518 | BL6: NA | BM6: NA | BN6: NA | BO6: NA | BP6: NA | BQ6: No
A7: ='Firm list'!B7 -> TRAPI | B7: NA | C7: 225 | D7: 215 | E7: 192 | F7: 220 | G7: 215 | H7: 209 | I7: 211 | J7: 205 | K7: 217 | L7: 249 | M7: 245 | N7: 245 | O7: Yes | S7: Tukuma Piens | T7: NA | U7: -6300366 | V7: -2669876 | W7: -486127 | X7: -1039595 | Y7: -4747020 | Z7: -7235548 | AA7: -2305741 | AB7: -2602981 | AC7: -3198365 | AD7: -1603849 | AE7: -2178797 | AF7: -2836636 | AG7: Yes | AK7: Tukuma Piens | AL7: NA | AM7: 94881767 | AN7: 88904649 | AO7: 76561185 | AP7: 65790286 | AQ7: 66371774 | AR7: 57894764 | AS7: 55097643 | AT7: 53186134 | AU7: 46129720 | AV7: 46910324 | AW7: 53194916 | AX7: 34659059 | AY7: Yes | BC7: Tukuma Piens | BD7: NA | BE7: 5184567 | BF7: 4806117 | BG7: 4016890 | BH7: 4288314 | BI7: 4055494 | BJ7: 3722845 | BK7: 3365089 | BL7: 3139804 | BM7: 3145921 | BN7: 2956365 | BO7: 2757012 | BP7: NA | BQ7: Yes
A8: ='Firm list'!B8 -> GP TEHNOPARKI | B8: 5 | C8: 5 | D8: 6 | E8: 6 | F8: 7 | G8: 4 | H8: 4 | I8: 5 | J8: 5 | K8: 2 | L8: 1 | M8: 0 | N8: NA | O8: Yes | S8: Vecās Ostmalas Biznesa Parks | T8: NA | U8: NA | V8: NA | W8: NA | X8: NA | Y8: NA | Z8: NA | AA8: NA | AB8: NA | AC8: NA | AD8: NA | AE8: NA | AF8: NA | AG8: No | AK8: Vecās Ostmalas Biznesa Parks | AL8: 946205 | AM8: 952020 | AN8: 746750 | AO8: 742267 | AP8: 552571 | AQ8: 481693 | AR8: 370145 | AS8: 243656 | AT8: 206622 | AU8: 145617 | AV8: 9037 | AW8: - | AX8: NA | AY8: No | AZ8: Just started this company, might get eschezed results | BC8: Vecās Ostmalas Biznesa Parks | BD8: 75399 | BE8: 82899 | BF8: 85687 | BG8: 83280 | BH8: 90409 | BI8: 58471 | BJ8: NA | BK8: NA | BL8: 52195 | BM8: 16095 | BN8: 2689 | BO8: - | BP8: NA | BQ8: No
A9: ='Firm list'!B9 -> NTC INVESTĪCIJAS | B9: 3 | C9: 3 | D9: 3 | E9: 3 | F9: 3 | G9: 2 | H9: 2 | I9: 2 | J9: 0 | K9: 0 | L9: NA | M9: NA | N9: NA | O9: No | S9: TRAPI | T9: NA | U9: NA | V9: NA | W9: NA | X9: NA | Y9: NA | Z9: NA | AA9: NA | AB9: NA | AC9: NA | AD9: NA | AE9: NA | AF9: NA | AG9: No | AK9: TRAPI | AL9: 243041 | AM9: 243041 | AN9: 250422 | AO9: 114369 | AP9: - | AQ9: 10000 | AR9: 31312 | AS9: 228115 | AT9: - | AU9: - | AV9: NA | AW9: NA | AX9: NA | AY9: No | BC9: TRAPI | BD9: 4598 | BE9: 4598 | BF9: 2545 | BG9: 2545 | BH9: 2461 | BI9: NA | BJ9: NA | BK9: NA | BL9: NA | BM9: NA | BN9: NA | BO9: NA | BP9: NA | BQ9: No
A10: ='Firm list'!B10 -> TENAX | B10: 0 | C10: 0 | D10: 2 | E10: 2 | F10: 1 | G10: 1 | H10: 6 | I10: 6 | J10: 5 | K10: 1 | L10: NA | M10: NA | N10: NA | O10: No | S10: GP TEHNOPARKI | T10: NA | U10: NA | V10: NA | W10: NA | X10: NA | Y10: NA | Z10: NA | AA10: NA | AB10: NA | AC10: NA | AD10: NA | AE10: NA | AF10: NA | AG10: No | AK10: GP TEHNOPARKI | AL10: NA | AM10: - | AN10: 74708 | AO10: 107901 | AP10: 24439 | AQ10: - | AR10: 127025 | AS10: 325213 | AT10: 171307 | AU10: - | AV10: - | AW10: NA | AX10: NA | AY10: No | BC10: GP TEHNOPARKI | BD10: NA | BE10: NA | BF10: NA | BG10: NA | BH10: NA | BI10: NA | BJ10: NA | BK10: 49309 | BL10: 36205 | BM10: 564 | BN10: NA | BO10: NA | BP10: NA | BQ10: No
A11: ='Firm list'!B11 -> IT INTERNATIONAL | B11: 1 | C11: 1 | D11: 0 | E11: 0 | F11: 0 | G11: 0 | H11: 0 | I11: 0 | J11: 0 | K11: 0 | L11: 0 | M11: 0 | N11: NA | O11: No | P11: Company was only founded in 2014 | S11: NTC INVESTĪCIJAS | T11: NA | U11: NA | V11: NA | W11: NA | X11: NA | Y11: NA | Z11: NA | AA11: NA | AB11: NA | AC11: NA | AD11: NA | AE11: NA | AF11: NA | AG11: No | AK11: NTC INVESTĪCIJAS | AL11: 282741 | AM11: 146105 | AN11: 199946 | AO11: 197464 | AP11: 138102 | AQ11: 47925 | AR11: 33540 | AS11: 20795 | AT11: 26928 | AU11: 24195 | AV11: 11994 | AW11: 5573 | AX11: - | AY11: Yes | BC11: NTC INVESTĪCIJAS | BD11: NA | BE11: NA | BF11: NA | BG11: NA | BH11: NA | BI11: NA | BJ11: NA | BK11: NA | BL11: NA | BM11: NA | BN11: NA | BO11: NA | BP11: NA | BQ11: No
A12: ='Firm list'!B12 -> iCotton | B12: NA | C12: 14 | D12: 13 | E12: 14 | F12: 14 | G12: 13 | H12: 15 | I12: 14 | J12: 7 | K12: 7 | L12: 17 | M12: 17 | N12: 18 | O12: Yes | S12: TENAX | T12: NA | U12: -77132 | V12: -594803 | W12: -6423429 | X12: -83175 | Y12: -816925 | Z12: -594680 | AA12: -609009 | AB12: -429404 | AC12: -142271 | AD12: -610060 | AE12: -207356 | AF12: 589920 | AG12: Yes | AK12: TENAX | AL12: NA | AM12: 2523326 | AN12: 2289351 | AO12: 1953241 | AP12: 1879027 | AQ12: 1694616 | AR12: 1641168 | AS12: 1053967 | AT12: 829543 | AU12: 743918 | AV12: 1626775 | AW12: 1843543 | AX12: 1272814 | AY12: Yes | BC12: TENAX | BD12: NA | BE12: 813588 | BF12: 747675 | BG12: 926191 | BH12: 596546 | BI12: 547118 | BJ12: 583351 | BK12: 508350 | BL12: 230115 | BM12: 347343 | BN12: 347343 | BO12: 487571 | BP12: NA | BQ12: Yes
A13: ='Firm list'!B13 -> Lyngson | B13: NA | C13: NA | D13: NA | E13: NA | F13: NA | G13: NA | H13: NA | I13: 1 | J13: 7 | K13: 12 | L13: 8 | M13: 9 | N13: 22 | O13: No | P13: Liquidated | S13: IT INTERNATIONAL | T13: NA | U13: NA | V13: NA | W13: NA | X13: NA | Y13: NA | Z13: NA | AA13: NA | AB13: NA | AC13: NA | AD13: NA | AE13: NA | AF13: -53530 | AG13: No | AH13: Liquidated | AK13: IT INTERNATIONAL | AL13: NA | AM13: NA | AN13: NA | AO13: NA | AP13: NA | AQ13: NA | AR13: NA | AS13: 226251 | AT13: 798995 | AU13: 1092818 | AV13: 1821154 | AW13: 1052571 | AX13: 748487 | AY13: No | AZ13: Liquidated | BC13: IT INTERNATIONAL | BD13: NA | BE13: NA | BF13: NA | BG13: NA | BH13: NA | BI13: NA | BJ13: NA | BK13: NA | BL13: 83073 | BM13: 47410 | BN13: 47410 | BO13: 32476 | BP13: NA | BQ13: No | BR13: Liquidated
A14: ='Firm list'!B14 -> Piebalgas | B14: 140 | C14: 143 | D14: 158 | E14: 152 | F14: 143 | G14: 111 | H14: 127 | I14: 168 | J14: 149 | K14: 150 | L14: 109 | M14: 64 | N14: 37 | O14: Yes | S14: iCotton | T14: -233604 | U14: -284287 | V14: -1027298 | W14: -1774292 | X14: -5160228 | Y14: -8476925 | Z14: -4258609 | AA14: -2614693 | AB14: -694074 | AC14: -668353 | AD14: -8631697 | AE14: -202782 | AF14: -1059775 | AG14: Yes | AK14: iCotton | AL14: 15689933 | AM14: 12086459 | AN14: 16159823 | AO14: 19637448 | AP14: 21658350 | AQ14: 28381032 | AR14: 26273886 | AS14: 25966495 | AT14: 18695782 | AU14: 9445222 | AV14: 5763079 | AW14: 5725894 | AX14: 619128 | AY14: Yes | BC14: iCotton | BD14: 3128387 | BE14: 3093707 | BF14: 3092067 | BG14: 2547168 | BH14: 1518246 | BI14: 1518246 | BJ14: 1733047 | BK14: 2093985 | BL14: 2364264 | BM14: 1488737 | BN14: 672843 | BO14: 653720 | BP14: NA | BQ14: Yes
A15: ='Firm list'!B15 -> Kronus | B15: NA | C15: 114 | D15: 127 | E15: 128 | F15: 128 | G15: 130 | H15: 134 | I15: 133 | J15: 112 | K15: 107 | L15: 108 | M15: 105 | N15: 98 | O15: Yes | S15: Lyngson | T15: NA | U15: -317491 | V15: -232340 | W15: -283242 | X15: -334659 | Y15: -511136 | Z15: -470762 | AA15: -1671437 | AB15: -1737524 | AC15: -1830314 | AD15: -85580 | AE15: -334174 | AF15: -532832 | AG15: Yes | AK15: Lyngson | AL15: NA | AM15: 11413608 | AN15: 15619301 | AO15: 18924058 | AP15: 14738615 | AQ15: 12803242 | AR15: 13518423 | AS15: 13893616 | AT15: 12435811 | AU15: 10654491 | AV15: 11053920 | AW15: 11695598 | AX15: 10639668 | AY15: Yes | BC15: Lyngson | BD15: NA | BE15: 2851532 | BF15: 2950920 | BG15: 2900028 | BH15: 2560867 | BI15: 2478486 | BJ15: 2431592 | BK15: 2263414 | BL15: 1800662 | BM15: 1599886 | BN15: 1567011 | BO15: 1444727 | BP15: NA | BQ15: Yes
A16: ='Firm list'!B16 -> NPK Expert | B16: 56 | C16: 57 | D16: 57 | E16: 62 | F16: 63 | G16: 63 | H16: 63 | I16: 66 | J16: 66 | K16: 68 | L16: 70 | M16: 79 | N16: 79 | O16: Yes | S16: Piebalgas | T16: NA | U16: NA | V16: -88041 | W16: -58223 | X16: NA | Y16: NA | Z16: NA | AA16: NA | AB16: NA | AC16: NA | AD16: NA | AE16: NA | AF16: -170450 | AG16: No | AK16: Piebalgas | AL16: 5798254 | AM16: 7761623 | AN16: 6933267 | AO16: 9545132 | AP16: 7055719 | AQ16: 6289412 | AR16: 5487576 | AS16: 6698241 | AT16: 6042284 | AU16: 5107709 | AV16: 5604600 | AW16: 7372334 | AX16: 6166301 | AY16: Yes | BC16: Piebalgas | BD16: 1090279 | BE16: 1085866 | BF16: 1067345 | BG16: 1050025 | BH16: 919445 | BI16: 877588 | BJ16: 786842 | BK16: 784012 | BL16: 674923 | BM16: 625967 | BN16: 53752 | BO16: 53860 | BP16: NA | BQ16: Yes
A17: ='Firm list'!B17 -> EcoLead | B17: NA | C17: 522 | D17: 565 | E17: 538 | F17: 542 | G17: 435 | H17: 356 | I17: 249 | J17: 249 | K17: 249 | L17: 249 | M17: 249 | N17: NA | O17: Yes | S17: Kronus | T17: NA | U17: -804655 | V17: -3464524 | W17: -4327471 | X17: -1407853 | Y17: -706522 | Z17: -1818664 | AA17: -1960177 | AB17: -2770758 | AC17: -2390968 | AD17: -845734 | AE17: NA | AF17: NA | AG17: Yes | AK17: Kronus | AL17: NA | AM17: 85969169 | AN17: 92892077 | AO17: 124736999 | AP17: 87752342 | AQ17: 44435198 | AR17: 41317816 | AS17: 49109610 | AT17: 39978056 | AU17: 31388492 | AV17: 28124373 | AW17: 28035477 | AX17: 27201561 | AY17: Yes | BC17: Kronus | BD17: NA | BE17: 16041514 | BF17: 17024003 | BG17: 16634533 | BH17: 12701848 | BI17: 10476639 | BJ17: 8053823 | BK17: 4421746 | BL17: 3893343 | BM17: 2401564 | BN17: 2130490 | BO17: 1927689 | BP17: 1867003 | BQ17: Yes
A18: ='Firm list'!B18 -> Carbon energy systems | B18: NA | C18: NA | D18: NA | E18: NA | F18: NA | G18: NA | H18: NA | I18: NA | J18: NA | K18: 3 | L18: 35 | M18: 33 | N18: 5 | O18: No | P18: Liquidated | S18: NPK Expert | T18: NA | U18: NA | V18: NA | W18: NA | X18: NA | Y18: NA | Z18: NA | AA18: NA | AB18: NA | AC18: NA | AD18: NA | AE18: -118259 | AF18: -32631 | AG18: No | AH18: Liquidated | AK18: NPK Expert | AL18: NA | AM18: NA | AN18: NA | AO18: NA | AP18: NA | AQ18: NA | AR18: NA | AS18: NA | AT18: NA | AU18: 14833532 | AV18: 15411195 | AW18: 10160767 | AX18: 2239475 | AY18: No | AZ18: Liquidated | BC18: NPK Expert | BD18: NA | BE18: NA | BF18: NA | BG18: NA | BH18: NA | BI18: NA | BJ18: NA | BK18: NA | BL18: NA | BM18: 342653 | BN18: 392052 | BO18: NA | BP18: NA | BQ18: No | BR18: Liquidated
A19: ='Firm list'!B19 -> JĒKABPILS PMK | B19: NA | C19: 44 | D19: 34 | E19: 9 | F19: 6 | G19: 4 | H19: 4 | I19: 3 | J19: 3 | K19: 2 | L19: 4 | M19: 6 | N19: 6 | O19: Yes | S19: EcoLead | T19: NA | U19: NA | V19: NA | W19: NA | X19: NA | Y19: NA | Z19: NA | AA19: NA | AB19: NA | AC19: NA | AD19: NA | AE19: NA | AF19: NA | AG19: No | AK19: EcoLead | AL19: NA | AM19: 9777770 | AN19: 4101929 | AO19: 180634 | AP19: 74629 | AQ19: NA | AR19: NA | AS19: NA | AT19: NA | AU19: NA | AV19: NA | AW19: NA | AX19: NA | AY19: No | BC19: EcoLead | BD19: NA | BE19: 1741232 | BF19: 953077 | BG19: 88791 | BH19: 42902 | BI19: NA | BJ19: NA | BK19: NA | BL19: NA | BM19: NA | BN19: 37808 | BO19: 48881 | BP19: 52387 | BQ19: No
A20: ='Firm list'!B20 -> AmberBirch | B20: 10 | C20: 9 | D20: 2 | E20: 1 | F20: 3 | G20: 3 | H20: 6 | I20: 1 | J20: 1 | K20: 2 | L20: 3 | M20: 3 | N20: 1 | O20: Yes | S20: Carbon energy systems | T20: NA | U20: NA | V20: NA | W20: NA | X20: NA | Y20: NA | Z20: NA | AA20: NA | AB20: NA | AC20: NA | AD20: NA | AE20: NA | AF20: NA | AG20: No | AK20: Carbon energy systems | AL20: 30117 | AM20: 9040 | AN20: - | AO20: - | AP20: - | AQ20: - | AR20: - | AS20: - | AT20: - | AU20: - | AV20: - | AW20: - | AX20: - | AY20: No | AZ20: Zero sales | BC20: Carbon energy systems | BD20: NA | BE20: NA | BF20: NA | BG20: NA | BH20: NA | BI20: NA | BJ20: NA | BK20: NA | BL20: NA | BM20: NA | BN20: NA | BO20: NA | BP20: NA | BQ20: No
A21: ='Firm list'!B21 -> VALMIERMUIŽAS ALUS | B21: NA | C21: 210 | D21: 236 | E21: 230 | F21: 243 | G21: 226 | H21: 229 | I21: 221 | J21: 205 | K21: 186 | L21: 226 | M21: 260 | N21: 233 | O21: Yes | S21: JĒKABPILS PMK | T21: NA | U21: -21317 | V21: -154089 | W21: -270442 | X21: -220385 | Y21: -1695600 | Z21: -926858 | AA21: -465145 | AB21: -886122 | AC21: -83611 | AD21: -68345 | AE21: -151478 | AF21: -81165 | AG21: Yes | AK21: JĒKABPILS PMK | AL21: NA | AM21: 17071487 | AN21: 24232828 | AO21: 21877095 | AP21: 18073713 | AQ21: 19101679 | AR21: 19698882 | AS21: 14667191 | AT21: 12483863 | AU21: 5790706 | AV21: 14239816 | AW21: 14805701 | AX21: 11332031 | AY21: Yes | BC21: JĒKABPILS PMK | BD21: NA | BE21: 4424782 | BF21: 4694489 | BG21: 4393840 | BH21: 4119197 | BI21: 4220024 | BJ21: 3981290 | BK21: 3474175 | BL21: 2990778 | BM21: 2314860 | BN21: 2851964 | BO21: NA | BP21: NA | BQ21: Yes
A22: ='Firm list'!B22 -> PUMAC LIEPAJA | B22: NA | C22: 87 | D22: 85 | E22: 83 | F22: 77 | G22: 60 | H22: 14 | I22: 1 | J22: 1 | K22: NA | L22: NA | M22: NA | N22: NA | O22: No | P22: Started operating in 2018 only | S22: AmberBirch | T22: NA | U22: -21591040 | V22: -2827778 | W22: -710188 | X22: -907520 | Y22: -217435 | Z22: NA | AA22: NA | AB22: NA | AC22: NA | AD22: NA | AE22: NA | AF22: NA | AG22: No | AK22: AmberBirch | AL22: NA | AM22: 21647336 | AN22: 26626401 | AO22: 24001131 | AP22: 12397598 | AQ22: 7420678 | AR22: 220236 | AS22: 48332 | AT22: 27907 | AU22: NA | AV22: NA | AW22: NA | AX22: NA | AY22: Yes | BC22: AmberBirch | BD22: NA | BE22: 3185787 | BF22: 2547673 | BG22: 2071993 | BH22: 1482843 | BI22: 1138944 | BJ22: 241300 | BK22: 36679 | BL22: 11962 | BM22: NA | BN22: NA | BO22: NA | BP22: NA | BQ22: Yes
A23: ='Firm list'!B23 -> CEWOOD | B23: 127 | C23: 120 | D23: 111 | E23: 67 | F23: 68 | G23: 71 | H23: 75 | I23: 68 | J23: 67 | K23: 63 | L23: 52 | M23: 41 | N23: 30 | O23: Yes | S23: VALMIERMUIŽAS ALUS | T23: -819474 | U23: -1000400 | V23: -306655 | W23: -951104 | X23: -317090 | Y23: -115629 | Z23: -155711 | AA23: -565719 | AB23: -615976 | AC23: -299209 | AD23: -466806 | AE23: -858128 | AF23: -559884 | AG23: Yes | AK23: VALMIERMUIŽAS ALUS | AL23: 10538765 | AM23: 10018435 | AN23: 9435322 | AO23: 7016988 | AP23: 5816047 | AQ23: 5517672 | AR23: 5683824 | AS23: 5372787 | AT23: 4605931 | AU23: 4226454 | AV23: 3840233 | AW23: 3387547 | AX23: 1751693 | AY23: Yes | BC23: VALMIERMUIŽAS ALUS | BD23: 3106203 | BE23: 2592386 | BF23: 2346967 | BG23: 1496431 | BH23: 1415745 | BI23: 1237768 | BJ23: 1240030 | BK23: 996041 | BL23: 897858 | BM23: 758006 | BN23: 1139550 | BO23: 368029 | BP23: NA | BQ23: Yes
A24: ='Firm list'!B24 -> VUDLANDE | B24: NA | C24: 6 | D24: 6 | E24: 6 | F24: 6 | G24: 6 | H24: 6 | I24: 7 | J24: 7 | K24: 7 | L24: 8 | M24: 10 | O24: Yes | S24: PUMAC LIEPAJA | T24: NA | U24: NA | V24: NA | W24: NA | X24: NA | Y24: NA | Z24: NA | AA24: NA | AB24: NA | AC24: NA | AD24: NA | AE24: NA | AF24: NA | AG24: No | AK24: PUMAC LIEPAJA | AL24: NA | AM24: 3293954 | AN24: 3238097 | AO24: 2702046 | AP24: 2631479 | AQ24: 2655026 | AR24: 2681245 | AS24: 2521113 | AT24: 2228728 | AU24: 2108053 | AV24: 1887778 | AW24: 1718895 | AX24: 1529904 | AY24: Yes | BC24: PUMAC LIEPAJA | BD24: NA | BE24: 117357 | BF24: 95116 | BG24: 88992 | BH24: 87401 | BI24: 81011 | BJ24: 74141 | BK24: 77664 | BL24: 73717 | BM24: 74668 | BN24: 81948 | BO24: 75037 | BP24: NA | BQ24: Yes
A25: ='Firm list'!B25 -> Artex Latvia | B25: NA | C25: 155 | D25: 131 | E25: 108 | F25: 103 | G25: 96 | H25: 103 | I25: 60 | J25: 35 | K25: 24 | L25: 2 | M25: 0 | N25: 0 | O25: Yes | S25: CEWOOD | T25: NA | U25: -5768347 | V25: -4554152 | W25: -7937831 | X25: -1583552 | Y25: -408265 | Z25: -605614 | AA25: NA | AB25: NA | AC25: NA | AD25: NA | AE25: NA | AF25: NA | AG25: No | AK25: CEWOOD | AL25: NA | AM25: 16449406 | AN25: 14655944 | AO25: 12945298 | AP25: 10178101 | AQ25: 7537714 | AR25: 6565998 | AS25: 4272962 | AT25: 1282637 | AU25: 422347 | AV25: - | AW25: - | AX25: - | AY25: Yes | BC25: CEWOOD | BD25: NA | BE25: 3300140 | BF25: 2563557 | BG25: 1962707 | BH25: 1673246 | BI25: 1367960 | BJ25: NA | BK25: 898202 | BL25: NA | BM25: NA | BN25: NA | BO25: NA | BP25: NA | BQ25: No
A26: ='Firm list'!B26 -> SFM Latvia | B26: 108 | C26: 108 | D26: 102 | E26: 135 | F26: 115 | G26: 104 | H26: 111 | I26: 98 | J26: 82 | K26: 74 | L26: 74 | M26: 74 | N26: 73 | O26: Yes | S26: VUDLANDE | T26: -3086890 | U26: -6399059 | V26: -6486869 | W26: -5089609 | X26: -2298728 | Y26: -2564153 | Z26: -3752044 | AA26: -1859123 | AB26: -694254 | AC26: -412864 | AD26: -446004 | AE26: -448193 | AF26: NA | AG26: Yes | AK26: VUDLANDE | AL26: 24291524 | AM26: 21696229 | AN26: 17603250 | AO26: 60877228 | AP26: 44136749 | AQ26: 17393548 | AR26: 22003118 | AS26: 19344872 | AT26: 14802416 | AU26: 12979124 | AV26: 12760446 | AW26: 11691990 | AX26: 10689176 | AY26: Yes | BC26: VUDLANDE | BD26: 2059977 | BE26: 1927637 | BF26: 1697772 | BG26: 2355024 | BH26: 2005075 | BI26: 1577942 | BJ26: 1344392 | BK26: 1275933 | BL26: 1039541 | BM26: 821444 | BN26: 702265 | BO26: 606780 | BP26: NA | BQ26: Yes
A27: ='Firm list'!B27 -> EB Liepāja | B27: 192 | C27: 220 | D27: 277 | E27: 246 | F27: 213 | G27: 206 | H27: 209 | I27: 174 | J27: 153 | K27: 101 | L27: 86 | M27: 70 | N27: 59 | O27: Yes | S27: Artex Latvia | T27: -27761 | U27: -367817 | V27: -201738 | W27: NA | X27: NA | Y27: NA | Z27: NA | AA27: NA | AB27: NA | AC27: NA | AD27: -13871 | AE27: -267955 | AF27: -2659 | AG27: No | AK27: Artex Latvia | AL27: 8632772 | AM27: 8217987 | AN27: 7428951 | AO27: 6776697 | AP27: 4557049 | AQ27: 3638136 | AR27: 4670600 | AS27: 4206259 | AT27: 3484504 | AU27: 2366918 | AV27: 1396566 | AW27: 869449 | AX27: 700882 | AY27: Yes | BC27: Artex Latvia | BD27: 2972372 | BE27: 2974450 | BF27: 3282672 | BG27: 2612167 | BH27: 2121118 | BI27: 1809384 | BJ27: 1888889 | BK27: 1539649 | BL27: 1336475 | BM27: 845867 | BN27: 692084 | BO27: 545361 | BP27: NA | BQ27: Yes
A28: ='Firm list'!B28 -> Stiga RM | B28: 95 | C28: 75 | D28: 68 | E28: 64 | F28: 72 | G28: 73 | H28: 76 | I28: 83 | J28: 78 | K28: 52 | L28: 39 | M28: 29 | N28: 30 | O28: Yes | S28: SFM Latvia | T28: -1398765 | U28: -1346395 | V28: -900568 | W28: -3641942 | X28: NA | Y28: NA | Z28: NA | AA28: NA | AB28: NA | AC28: NA | AD28: -929301 | AE28: -2017 | AF28: -15756 | AG28: No | AK28: SFM Latvia | AL28: 13132882 | AM28: 10931159 | AN28: 8192943 | AO28: 10851636 | AP28: 6943767 | AQ28: 5285319 | AR28: 5537013 | AS28: 5621652 | AT28: 6047473 | AU28: 5000487 | AV28: 3065305 | AW28: 1992739 | AX28: 1520335 | AY28: Yes | BC28: SFM Latvia | BD28: 3225805 | BE28: 2309979 | BF28: 1629182 | BG28: 1393631 | BH28: 1414101 | BI28: 1433753 | BJ28: 1384031 | BK28: 1418286 | BL28: NA | BM28: 731302 | BN28: 228862 | BO28: 150255 | BP28: NA | BQ28: No
A29: ='Firm list'!B29 -> Haugaard Baltic | B29: 0 | C29: 0 | D29: 0 | E29: 0 | F29: 0 | G29: 0 | H29: 0 | I29: 0 | J29: NA | K29: NA | L29: NA | M29: NA | N29: NA | O29: No | P29: 0 employee company | S29: EB Liepāja | T29: NA | U29: NA | V29: NA | W29: NA | X29: NA | Y29: NA | Z29: NA | AA29: NA | AB29: NA | AC29: NA | AD29: NA | AE29: NA | AF29: NA | AG29: No | AK29: EB Liepāja | AL29: 360000 | AM29: 360000 | AN29: 34000 | AO29: - | AP29: - | AQ29: - | AR29: - | AS29: - | AT29: NA | AU29: NA | AV29: NA | AW29: NA | AX29: NA | AY29: No | BC29: EB Liepāja | BD29: - | BE29: - | BF29: - | BG29: - | BH29: - | BI29: - | BJ29: - | BK29: - | BL29: NA | BM29: NA | BN29: NA | BO29: NA | BP29: NA | BQ29: No
A30: ='Firm list'!B30 -> IKTK | B30: NA | C30: 409 | D30: 350 | E30: 304 | F30: 248 | G30: 222 | H30: 200 | I30: 238 | J30: 176 | K30: 99 | L30: 141 | M30: 67 | N30: 56 | O30: Yes | S30: Stiga RM | T30: NA | U30: -36286841 | V30: -28721635 | W30: -19957951 | X30: -4581057 | Y30: -11154747 | Z30: -6279069 | AA30: -9256829 | AB30: -506149 | AC30: -1351776 | AD30: -4765085 | AE30: -2754322 | AF30: -1405376 | AG30: Yes | AK30: Stiga RM | AL30: NA | AM30: 80058988 | AN30: 76554323 | AO30: 69161043 | AP30: 43052077 | AQ30: 23918559 | AR30: 20553989 | AS30: 24177895 | AT30: 16548536 | AU30: 13549693 | AV30: 9287255 | AW30: 8968714 | AX30: 8190870 | AY30: Yes | BC30: Stiga RM | BD30: NA | BE30: 11449134 | BF30: 9361117 | BG30: 6822684 | BH30: 4789287 | BI30: 3880637 | BJ30: 3222820 | BK30: 3837226 | BL30: 2230384 | BM30: 1119927 | BN30: 1013675 | BO30: 627283 | BP30: NA | BQ30: Yes
A31: ='Firm list'!B31 -> Scan-Plast Latvia | B31: 114 | C31: 96 | D31: 93 | E31: 112 | F31: 88 | G31: 65 | H31: 57 | I31: 34 | J31: 25 | K31: 12 | L31: 6 | M31: 0 | N31: 0 | O31: Yes | S31: Haugaard Baltic | T31: -428126 | U31: -230601 | V31: -409519 | W31: -108831 | X31: -151985 | Y31: -49774 | Z31: NA | AA31: NA | AB31: NA | AC31: -39565 | AD31: -16462 | AE31: - | AF31: - | AG31: No | AK31: Haugaard Baltic | AL31: 12967428 | AM31: 11584163 | AN31: 12265731 | AO31: 16456435 | AP31: 12636456 | AQ31: 6427336 | AR31: 5661379 | AS31: 3097029 | AT31: 2008675 | AU31: 898183 | AV31: 272556 | AW31: - | AX31: - | AY31: Yes | BC31: Haugaard Baltic | BD31: 3411212 | BE31: 2809764 | BF31: 2530024 | BG31: 2917978 | BH31: 2197555 | BI31: 1509148 | BJ31: 1238382 | BK31: 473897 | BL31: 182779 | BM31: 195454 | BN31: 68599 | BO31: NA | BP31: NA | BQ31: Yes
A32: ='Firm list'!B32 -> texmex | B32: 54 | C32: 49 | D32: 45 | E32: 37 | F32: 24 | G32: 19 | H32: 18 | I32: 14 | J32: 9 | K32: 5 | L32: 4 | M32: 1 | N32: 0 | O32: Yes | S32: IKTK | T32: NA | U32: NA | V32: NA | W32: NA | X32: NA | Y32: NA | Z32: NA | AA32: NA | AB32: NA | AC32: NA | AD32: NA | AE32: NA | AF32: NA | AG32: No | AK32: IKTK | AL32: 5925696 | AM32: 5080492 | AN32: 5612526 | AO32: 3423393 | AP32: 2634776 | AQ32: 1301518 | AR32: 1262077 | AS32: 1187395 | AT32: 550111 | AU32: 314743 | AV32: 486957 | AW32: - | AX32: - | AY32: Yes | BC32: IKTK | BD32: NA | BE32: NA | BF32: NA | BG32: NA | BH32: NA | BI32: NA | BJ32: NA | BK32: NA | BL32: NA | BM32: NA | BN32: NA | BO32: NA | BP32: NA | BQ32: No
A33: ='Firm list'!B33 -> JELGAVAS TIPOGRĀFIJA | B33: 51 | C33: 51 | D33: 53 | E33: 52 | F33: 53 | G33: 61 | H33: 58 | I33: 64 | J33: 63 | K33: 61 | L33: 72 | M33: 68 | N33: 80 | O33: Yes | S33: Scan-Plast Latvia | T33: -118912 | U33: -238123 | V33: -118466 | W33: -284027 | X33: -214614 | Y33: -410425 | Z33: -77762 | AA33: -36500 | AB33: -55968 | AC33: -65014 | AD33: -287231 | AE33: -29131 | AF33: NA | AG33: Yes | AK33: Scan-Plast Latvia | AL33: 4409458 | AM33: 4123429 | AN33: 4663818 | AO33: 2762710 | AP33: 3060795 | AQ33: 3688854 | AR33: 3215495 | AS33: 2737013 | AT33: 3273100 | AU33: 2153098 | AV33: 3363649 | AW33: 2832111 | AX33: - | AY33: Yes | BC33: Scan-Plast Latvia | BD33: 1342013 | BE33: 1058653 | BF33: 1017789 | BG33: 943043 | BH33: 913335 | BI33: 957362 | BJ33: 942729 | BK33: 899923 | BL33: NA | BM33: NA | BN33: 880793 | BO33: 828720 | BP33: NA | BQ33: Yes
A34: ='Firm list'!B34 -> ICS Property | B34: NA | C34: NA | D34: NA | E34: NA | F34: NA | G34: NA | H34: NA | I34: NA | J34: NA | K34: NA | L34: NA | M34: NA | N34: NA | O34: No | S34: texmex | T34: NA | U34: NA | V34: NA | W34: NA | X34: NA | Y34: NA | Z34: NA | AA34: NA | AB34: NA | AC34: NA | AD34: NA | AE34: NA | AF34: NA | AG34: No | AK34: texmex | AL34: NA | AM34: NA | AN34: NA | AO34: NA | AP34: NA | AQ34: NA | AR34: NA | AS34: NA | AT34: NA | AU34: NA | AV34: NA | AW34: NA | AX34: NA | AY34: No | BC34: texmex | BD34: NA | BE34: NA | BF34: NA | BG34: NA | BH34: NA | BI34: NA | BJ34: NA | BK34: NA | BL34: NA | BM34: NA | BN34: NA | BO34: NA | BP34: NA | BQ34: No
A35: ='Firm list'!B35 -> VIZULO | B35: 197 | C35: 194 | D35: 197 | E35: 198 | F35: 177 | G35: 156 | H35: 163 | I35: 144 | J35: 129 | K35: 123 | L35: 124 | M35: 111 | N35: 112 | O35: Yes | S35: JELGAVAS TIPOGRĀFIJA | T35: -2258310 | U35: -1097993 | V35: -866605 | W35: -156125 | X35: -1205432 | Y35: -2311256 | Z35: -796205 | AA35: -384671 | AB35: -252518 | AC35: -135721 | AD35: -453463 | AE35: -2455264 | AF35: -283456 | AG35: Yes | AK35: JELGAVAS TIPOGRĀFIJA | AL35: 18314322 | AM35: 17134906 | AN35: 17704991 | AO35: 17827403 | AP35: 14017593 | AQ35: 10569009 | AR35: 11659953 | AS35: 11444636 | AT35: 9814691 | AU35: 9655161 | AV35: 8664574 | AW35: 7575491 | AX35: 5637899 | AY35: Yes | BC35: JELGAVAS TIPOGRĀFIJA | BD35: 5101861 | BE35: 4968657 | BF35: 4636388 | BG35: 4240298 | BH35: 3729508 | BI35: 2840370 | BJ35: 3351050 | BK35: 2489696 | BL35: 2440655 | BM35: 2276246 | BN35: 2177535 | BO35: 1821347 | BP35: NA | BQ35: Yes
A36: ='Firm list'!B36 -> 0 | B36: 2 | C36: 2 | D36: 2 | E36: 2 | F36: 2 | G36: 2 | H36: 2 | I36: NA | J36: NA | K36: NA | L36: NA | M36: NA | N36: NA | O36: No | S36: ICS Property | T36: NA | U36: NA | V36: NA | W36: NA | X36: NA | Y36: NA | Z36: NA | AA36: NA | AB36: NA | AC36: NA | AD36: NA | AE36: NA | AF36: NA | AG36: No | AK36: ICS Property | AL36: 176134 | AM36: 176134 | AN36: - | AO36: - | AP36: - | AQ36: - | AR36: - | AS36: NA | AT36: NA | AU36: NA | AV36: NA | AW36: NA | AX36: NA | AY36: No | BC36: ICS Property | BD36: NA | BE36: NA | BF36: NA | BG36: NA | BH36: NA | BI36: NA | BJ36: NA | BK36: NA | BL36: NA | BM36: NA | BN36: NA | BO36: NA | BP36: NA | BQ36: No
A37: ='Firm list'!B37 -> 0 | B37: NA | C37: 154 | D37: 169 | E37: 117 | F37: 98 | G37: 114 | H37: 99 | I37: 73 | J37: 54 | K37: 45 | L37: 44 | M37: 20 | N37: 10 | O37: Yes | S37: VIZULO | T37: NA | U37: -2245446 | V37: -2114029 | W37: -522808 | X37: -603234 | Y37: -889401 | Z37: -931719 | AA37: -505705 | AB37: -142797 | AC37: -1036000 | AD37: -398430 | AE37: -567928 | AF37: -159830 | AG37: Yes | AK37: VIZULO | AL37: NA | AM37: 14708042 | AN37: 15742864 | AO37: 10853349 | AP37: 8891546 | AQ37: 12897734 | AR37: 10012999 | AS37: 8062834 | AT37: 5503911 | AU37: 2556235 | AV37: 6069438 | AW37: 2860662 | AX37: 199481 | AY37: Yes | BC37: VIZULO | BD37: NA | BE37: 2780903 | BF37: 2453338 | BG37: 1842952 | BH37: 1454460 | BI37: 1612047 | BJ37: 1530187 | BK37: 1120928 | BL37: 659831 | BM37: 413344 | BN37: 173955 | BO37: 61985 | BP37: NA | BQ37: Yes
N39: Total passing | O39: =COUNTIF(O4:O37,"yes") -> 24 | AF39: Total passing | AG39: 13 | AX39: Total passing | AY39: 24
A41: Emlpoyees NR | B41: 2025 | C41: 2024 | D41: =C41-1 -> 2023 | E41: =D41-1 -> 2022 | F41: =E41-1 -> 2021 | G41: =F41-1 -> 2020 | H41: =G41-1 -> 2019 | I41: =H41-1 -> 2018 | J41: =I41-1 -> 2017 | K41: =J41-1 -> 2016 | ... N41: =M41-1 -> 2013 | O41: DATA FIT | P41: Notes | T41: 2025 | U41: 2024 | V41: 2023 | W41: 2022 | X41: 2021 | Y41: 2020 | Z41: 2019 | AA41: 2018 | AB41: 2017 | AC41: 2016 | AD41: 2015 | AE41: 2014 | AF41: 2013 | AL41: 2025 | AM41: 2024 | AN41: 2023 | AO41: 2022 | AP41: 2021 | AQ41: 2020 | AR41: 2019 | AS41: 2018 | AT41: 2017 | AU41: 2016 | AV41: 2015 | AW41: 2014 | AX41: 2013
A42: BELMAST | H42: 165 | I42: 189 | J42: 191 | K42: 168 | L42: 200 | M42: 226 | S42: BELMAST | Z42: 50808 | AA42: 89507 | AB42: 117481 | AC42: 117407 | AD42: 61946 | AE42: 271472 | AK42: BELMAST | AR42: 11643196 | AS42: 8351746 | AT42: 8995022 | AU42: 7786052 | AV42: 7353872 | AW42: 9179681
A43: AMATEKS | H43: 43 | I43: 49 | J43: 49 | K43: 46 | L43: 37 | M43: 34 | AK43: AMATEKS | AR43: 2369885 | AS43: 2512476 | AT43: 3023378 | AU43: 2632440 | AV43: 1810346 | AW43: 1271659
AK44: FIND REPLACEMENT
A45: Latvijas maiznieks | H45: 276 | I45: 274 | J45: 252 | K45: 264 | L45: 269 | M45: 249 | S45: Latvijas maiznieks | Z45: -795996 | AA45: -1859065 | AB45: -4392493 | AC45: -1839087 | AD45: -1418863 | AE45: -5693692 | AK45: Latvijas maiznieks | AR45: 33737121 | AS45: 28720476 | AT45: 26185754 | AU45: 25033375 | AV45: 23948682 | AW45: 21643930
A46: LES TRANS | H46: 5 | I46: 4 | J46: 6 | K46: 8 | L46: 8 | M46: 10
AK49: FIND ANOTHER
A50: CompositeLine | H50: 13 | I50: 10 | J50: 11 | K50: 14 | L50: 11 | M50: 7 | S50: FIND ANOTHER | AK50: CompositeLine | AR50: 567622 | AS50: 376180 | AT50: 409005 | AU50: 710845 | AV50: 618092 | AW50: 323494
A52: AS BIOLARS | G52: 169 | H52: 170 | I52: 175 | J52: 183 | K52: 189 | L52: 199 | S52: AS BIOLARS | Y52: -318437 | Z52: -100511 | AA52: -165155 | AB52: -326772 | AC52: -785129 | AD52: -262073 | AK52: AS BIOLARS | AQ52: 15170337 | AR52: 18045219 | AS52: 17589693 | AT52: 15332865 | AU52: 14971034 | AV52: 15300250
A53: RK METALS | G53: 210 | H53: 214 | I53: 203 | J53: 184 | K53: 171 | L53: 158 | S53: RK METALS | Y53: -303079 | Z53: -246954 | AA53: -278814 | AB53: -236859 | AC53: -166093 | AD53: -855985 | AK53: RK METALS | AQ53: 23207254 | AR53: 23265077 | AS53: 21305276 | AT53: 14060953 | AU53: 12682480 | AV53: 12720505
A54: VEKTRA-21 | G54: 34 | H54: 37 | I54: 35 | J54: 28 | K54: 28 | L54: 23 | AK54: VEKTRA-21 | AQ54: 1592957 | AR54: 1564125 | AS54: 1212178 | AT54: 786086 | AU54: 696888 | AV54: 568083
A55: Gaujas koks | G55: 357 | H55: 343 | I55: 372 | J55: 433 | K55: 489 | L55: 447 | S55: Gaujas koks | Y55: -6131561 | Z55: -5727820 | AA55: -8490818 | AB55: -7576674 | AC55: -3835203 | AD55: -2750614 | AK55: Gaujas koks | AQ55: 76267426 | AR55: 66057285 | AS55: 82420197 | AT55: 60837807 | AU55: 65794604 | AV55: 59899767
A57: PLUTOS SELL | G57: 6 | H57: 6 | I57: 6 | J57: 5 | K57: 5 | L57: 3
A58: Baltic new technologies | G58: 1 | H58: 1 | I58: 1 | J58: 5 | K58: 5 | L58: 3
A59: AIMASA | E59: 103 | F59: 121 | G59: 123 | H59: 116 | I59: 100 | J59: 57 | S59: AIMASA | W59: -780536 | X59: -213245 | Y59: -547913 | Z59: -139983 | AA59: -160241 | AB59: -505948 | AK59: AIMASA | AO59: 45179988 | AP59: 32061744 | AQ59: 34112185 | AR59: 40542567 | AS59: 17828939 | AT59: 13194079
H60: 75 | AK60: FIND A YOUNG ONE
A61: Bauskas alus | E61: 61 | F61: 64 | G61: 64 | H61: 75 | I61: 75 | J61: 75 | S61: FIND ANOTHER | AK61: Bauskas alus | AO61: 7299667 | AP61: 6903114 | AQ61: 6779422 | AR61: 7629038 | AS61: 7423729 | AT61: 5226240
A62: Lion Estate | E62: 22 | F62: 19 | G62: 7 | H62: 4 | I62: 3 | J62: 8 | AK62: Lion Estate | AO62: 243730 | AP62: 860552 | AQ62: 509156 | AR62: 535380 | AS62: 255219 | AT62: 177766
A63: LODE SIA | E63: 144 | F63: 161 | G63: 161 | H63: 161 | I63: 155 | J63: 151 | AK63: LODE SIA | AO63: 14968605 | AP63: 14393708 | AQ63: 12522057 | AR63: 12009005 | AS63: 13125057 | AT63: 11251624
A64: GBM | E64: 76 | F64: 78 | G64: 74 | H64: 78 | I64: 85 | J64: 89 | S64: GBM | W64: -56039 | X64: -111061 | Y64: -121522 | Z64: -38531 | AA64: -66453 | AB64: -15409 | AK64: GBM | AO64: 5477107 | AP64: 4667996 | AQ64: 3485828 | AR64: 3699502 | AS64: 3587986 | AT64: 3234182
A65: Lauma Fabrics | E65: 360 | F65: 367 | G65: 384 | H65: 422 | I65: 452 | J65: 446 | AK65: Lauma Fabrics | AO65: 31961940 | AP65: 29065121 | AQ65: 24545570 | AR65: 32227521 | AS65: 31909132 | AT65: 32513187
A66: LATSTAB, RSEZ | E66: 66 | F66: 51 | G66: 48 | H66: 50 | I66: 39 | J66: 36 | AK66: LATSTAB, RSEZ | AO66: 4658940 | AP66: 2396100 | AQ66: 1977373 | AR66: 2211178 | AS66: 1874312 | AT66: 1614744
A68: Rettenmeier Baltic Timber | D68: 244 | E68: 263 | F68: 273 | G68: 295 | H68: 296 | I68: 301 | S68: Rettenmeier Baltic Timber | V68: -28255770 | W68: -12963141 | X68: -4465839 | Y68: -9019410 | Z68: -3603231 | AA68: -7607923 | AK68: Rettenmeier Baltic Timber | AN68: 90499158 | AO68: 80285744 | AP68: 58572768 | AQ68: 64078285 | AR68: 66431261 | AS68: 57723512
A69: HOPPEKIDS | D69: 59 | E69: 71 | F69: 106 | G69: 96 | H69: 88 | I69: 86 | AK69: HOPPEKIDS | AN69: 3436003 | AO69: 3389772 | AP69: 3793563 | AQ69: 4519585 | AR69: 3289652 | AS69: 3585452
A70: Celinieks | D70: 40 | E70: 36 | F70: 38 | G70: 35 | H70: 34 | I70: 33 | AK70: Celinieks | AN70: 1364420 | AO70: 2096159 | AP70: 1476762 | AQ70: 1675623 | AR70: 1489434 | AS70: 2044223
A71: Immer Digital | D71: 46 | E71: 42 | F71: 31 | G71: 33 | H71: 48 | I71: 64 | S71: FIND ANOTHER | AK71: Immer Digital | AN71: 2075301 | AO71: 2065920 | AP71: 1373632 | AQ71: 1123166 | AR71: 2331137 | AS71: 3643016
A73: PNB Print | D73: 251 | E73: 291 | F73: 300 | G73: 311 | H73: 297 | I73: 271 | S73: PNB Print | V73: -332749 | W73: -1173667 | X73: -1179195 | Y73: -511609 | Z73: -414419 | AA73: -418961 | AK73: PNB Print | AN73: 24026891 | AO73: 25058580 | AP73: 24434167 | AQ73: 21759842 | AR73: 24218653 | AS73: 22996221
A75: SIA MMG Group | C75: 35 | D75: 38 | E75: 31 | F75: 30 | G75: 26 | H75: 18 | S75: FIND ANOTHER | AK75: SIA MMG Group | AM75: 1852429 | AN75: 2170986 | AO75: 2182280 | AP75: 1748707 | AQ75: 1017757 | AR75: 774881

Sheet Tangible assets
A1: zemesgabali, ēkas un inženierbūves | B1: 2025 | C1: 2024 | D1: =C1-1 -> 2023 | E1: =D1-1 -> 2022 | F1: =E1-1 -> 2021 | G1: =F1-1 -> 2020 | H1: =G1-1 -> 2019 | I1: =H1-1 -> 2018 | J1: =I1-1 -> 2017 | K1: =J1-1 -> 2016 | ... N1: =M1-1 -> 2013 | O1: DATA FIT | P1: Notes
A2: Mārupes Metālmeistars | B2: 849382 | C2: 921481 | D2: 993581 | E2: 1411863 | F2: 1523872 | G2: 1224716 | H2: 1295454 | I2: 1366191 | J2: 1436929 | K2: 1505356 | L2: 1204414 | M2: 224210 | N2: 0 | O2: Yes
A3: TECNOPALI NORTH EUROPE | B3: NA | C3: 2767366 | D3: 2914748 | E3: 3057176 | F3: 3199604 | G3: 3245265 | H3: 3293100 | I3: 3420402 | J3: 1397816 | K3: 1422694 | L3: 1447572 | M3: 1378247 | N3: 789096 | O3: Yes
A4: Ventspils Brīvostas pārvalde | B4: 139108759 | C4: 145268079 | D4: 142122600 | E4: 140575842 | F4: 144967879 | G4: 133856770 | H4: 129774564 | I4: 126654918 | J4: 124964193 | K4: 129069629 | L4: 123148623 | M4: 76328492 | N4: 52187080 | O4: Yes
A5: Tukuma Piens | B5: NA | C5: 9003882 | D5: 9102898 | E5: 9065329 | F5: 9262404 | G5: 9449667 | H5: 5513004 | I5: 3724991 | J5: 3712998 | K5: 1580416 | L5: 1881465 | M5: 2441059 | N5: 2531156 | O5: Yes
A6: Vecās Ostmalas Biznesa Parks | B6: 6520012 | C6: 6051306 | D6: 4049648 | E6: 3997021 | F6: 3707042 | G6: 2817579 | H6: 2259510 | I6: 384603 | J6: 407948 | K6: 107539 | L6: 0 | M6: 0 | N6: NA | O6: No | P6: Jump from zero
A7: TRAPI | B7: 3006951 | C7: 3068188 | D7: 3194938 | E7: 3257585 | F7: 146093 | G7: 146093 | H7: 146093 | I7: 146093 | J7: 199000 | K7: 199000 | L7: NA | M7: NA | N7: NA | O7: No
A8: GP TEHNOPARKI | B8: NA | C8: NA | D8: 0 | E8: 1506766 | F8: 1529711 | G8: 393000 | H8: 125000 | I8: 715854 | J8: 749333 | K8: 0 | L8: 0 | M8: NA | N8: NA | O8: No
A9: NTC INVESTĪCIJAS | B9: 3088747 | C9: 4245326 | D9: 3071078 | E9: 3122220 | F9: 3223520 | G9: 331709 | H9: 612344 | I9: 506526 | J9: 523852 | K9: 536017 | L9: 194005 | M9: 433576 | N9: 0 | O9: Yes
A10: TENAX | B10: NA | C10: 9026394 | D10: 9567324 | E10: 3440123 | F10: 3396715 | G10: 2800916 | H10: 2845565 | I10: 2550405 | J10: 2269896 | K10: 0 | L10: 0 | M10: 0 | N10: 0 | O10: No | P10: Company was only founded in 2014
A11: IT INTERNATIONAL | B11: NA | C11: NA | D11: NA | E11: NA | F11: NA | G11: NA | H11: NA | I11: 216061 | J11: 21606 | K11: 224218 | L11: 72231 | M11: 0 | N11: 0 | O11: No | P11: Liquidated
A12: iCotton | B12: 5063026 | C12: 5325274 | D12: 5554321 | E12: 5817620 | F12: 6080919 | G12: 1529767 | H12: 1537729 | I12: 1423525 | J12: 1301664 | K12: 1341291 | L12: 255874 | M12: 292105 | N12: 227699 | O12: Yes
A13: Lyngson | B13: NA | C13: 4571107 | D13: 4628491 | E13: 4833232 | F13: 4936097 | G13: 4758628 | H13: 4926686 | I13: 5013933 | J13: 5559156 | K13: =3644848+299998 -> 3944846 | L13: =299998+4086648 -> 4386646 | M13: 0 | N13: 0 | O13: Yes
A14: Piebalgas | B14: 50861 | C14: 51908 | D14: 57164 | E14: 62420 | F14: 68417 | G14: 69373 | H14: 76939 | I14: 59248 | J14: 62602 | K14: 72380 | L14: 78516 | M14: 84801 | N14: 63505 | O14: Yes
A15: Kronus | B15: NA | C15: 4611073 | D15: 5098668 | E15: 5288594 | F15: 5302838 | G15: 5844322 | H15: 6255526 | I15: 5366276 | J15: 5638783 | K15: 4046596 | L15: 3682944 | M15: 3682945 | N15: 0 | O15: Yes
A16: NPK Expert | B16: NA | C16: NA | D16: NA | E16: NA | F16: NA | G16: NA | H16: NA | I16: NA | J16: NA | K16: 0 | L16: 0 | M16: 0 | N16: 0 | O16: No | P16: Liquidated
A17: EcoLead | B17: NA | C17: 5425698 | D17: 5521957 | E17: 53774 | F17: 57196 | G17: 60617 | H17: 64039 | I17: 67461 | J17: 70883 | K17: 74305 | L17: 77727 | M17: 81148 | N17: 84570 | O17: Yes
A18: Carbon energy systems | B18: 6328 | C18: 6328 | D18: 6328 | E18: 6328 | F18: 6328 | G18: 6328 | H18: 6328 | I18: 6328 | J18: 0 | K18: 0 | L18: 0 | M18: 0 | N18: 0 | O18: No | P18: Jump from zero
A19: JĒKABPILS PMK | B19: NA | C19: 2008120 | D19: 2123267 | E19: 2240413 | F19: 2398099 | G19: 2511497 | H19: 852361 | I19: 821849 | J19: 796595 | K19: 224214 | L19: 229755 | M19: 235319 | N19: 240882 | O19: Yes
A20: AmberBirch | B20: NA | C20: 6600611 | D20: 6683174 | E20: 6532090 | F20: 6384400 | G20: 6575542 | H20: 6850019 | I20: 512271 | J20: 51271 | K20: 0 | L20: NA | M20: NA | N20: NA | O20: Yes
A21: VALMIERMUIŽAS ALUS | B21: 2236206 | C21: 1971489 | D21: 2104722 | E21: 2152549 | F21: 1901363 | G21: 1984434 | H21: 2054532 | I21: 1828794 | J21: 1901816 | K21: 1861857 | L21: 1920348 | M21: 1986230 | N21: 1395810 | O21: Yes
A22: PUMAC LIEPAJA | B22: NA | C22: 17614082 | D22: 21357120 | E22: 19044382 | F22: 15352460 | G22: 15508672 | H22: 15160120 | I22: 12731802 | J22: 12618172 | K22: 12047620 | L22: 0 | M22: 0 | N22: 0 | O22: Yes
A23: CEWOOD | B23: NA | C23: 8644495 | D23: 8890247 | E23: 5544522 | F23: 117149 | G23: 0 | H23: 0 | I23: 0 | J23: 0 | K23: 0 | L23: 0 | M23: 0 | N23: 0 | O23: No | P23: Jump from zero
A24: VUDLANDE | B24: 5466253 | C24: 5315632 | D24: 5647458 | E24: 2655195 | F24: 2190030 | G24: 2254924 | H24: 1212477 | I24: 727758 | J24: 754291 | K24: 836328 | L24: 978281 | M24: 1096152 | N24: 1158304 | O24: Yes
A25: Artex Latvia | B25: 1653444 | C25: 1684816 | D25: 1716188 | E25: 1747560 | F25: 1778932 | G25: 1810314 | H25: 0 | I25: 0 | J25: 0 | K25: 0 | L25: 0 | M25: 0 | N25: 0 | O25: No | P25: Jump from zero
A26: SFM Latvia | B26: 3609218 | C26: 3674277 | D26: 3805034 | E26: 115000 | F26: 115000 | G26: 115000 | H26: 115000 | I26: 0 | J26: 0 | K26: 0 | L26: 0 | M26: 0 | N26: 0 | O26: No | P26: Jump from zero
A27: EB Liepāja | B27: 3384621 | C27: 3519046 | D27: 3653470 | E27: 3664672 | F27: 0 | G27: 0 | H27: 0 | I27: 0 | J27: NA | K27: NA | L27: NA | M27: NA | N27: NA | O27: No
A28: Stiga RM | B28: NA | C28: 18401358 | D28: 9620677 | E28: =8901571 -> 8901571 | F28: 8622093 | G28: 8641751 | H28: 6491348 | I28: 6711642 | J28: 4388068 | K28: 848810 | L28: 526927 | M28: 526927 | N28: 383470 | O28: Yes
A29: Haugaard Baltic | B29: 0 | C29: 0 | D29: 0 | E29: 0 | F29: 0 | G29: 0 | H29: 0 | I29: 0 | J29: 0 | K29: 0 | L29: 0 | M29: 0 | N29: 0 | O29: No | P29: Supposedly zero assets
A30: IKTK | B30: 4181964 | C30: 4453900 | D30: 4669834 | E30: 2374305 | F30: 2543159 | G30: 2712012 | H30: 2880865 | I30: 1363715 | J30: 1450055 | K30: 1536396 | L30: 1566919 | M30: 0 | N30: 0 | O30: Yes
A31: Scan-Plast Latvia | B31: 158632 | C31: 175617 | D31: 193058 | E31: 211275 | F31: 229492 | G31: 247709 | H31: 265926 | I31: 284143 | J31: 295955 | K31: 105386 | L31: 85431 | M31: 92424 | N31: 0 | O31: Yes
A32: texmex | B32: NA | C32: NA | D32: NA | E32: NA | F32: NA | G32: NA | H32: NA | I32: NA | J32: NA | K32: NA | L32: NA | M32: NA | N32: NA | O32: No
A33: JELGAVAS TIPOGRĀFIJA | B33: 4399278 | C33: 4604096 | D33: 4825644 | E33: 4581318 | F33: 4779786 | G33: 1711704 | H33: 1779053 | I33: 1825607 | J33: 1719437 | K33: 1751068 | L33: 1728893 | M33: 1623969 | N33: 1187998 | O33: Yes
A34: ICS Property | B34: 2583601 | C34: 2727134 | D34: 2837609 | E34: 0 | F34: 0 | G34: 0 | H34: 0 | I34: NA | J34: NA | K34: NA | L34: NA | M34: NA | N34: NA | O34: No
A35: VIZULO | B35: NA | C35: 0 | D35: 0 | E35: 0 | F35: 0 | G35: 0 | H35: 0 | I35: 0 | J35: 0 | K35: 0 | L35: 0 | M35: 0 | N35: 0 | O35: IDK | P35: Supposedly zero assets
N37: Total passing | O37: =COUNTIF(O2:O35,"yes") -> 19
B39: 2025 | C39: 2024 | D39: =C39-1 -> 2023 | E39: =D39-1 -> 2022 | F39: =E39-1 -> 2021 | G39: =F39-1 -> 2020 | H39: =G39-1 -> 2019 | I39: =H39-1 -> 2018 | J39: =I39-1 -> 2017 | K39: =J39-1 -> 2016 | ... N39: =M39-1 -> 2013
A40: BELMAST
A41: AMATEKS
A43: Latvijas maiznieks
A44: LES TRANS
A48: CompositeLine
A50: AS BIOLARS
A51: RK METALS
A52: VEKTRA-21
A53: Gaujas koks
A55: PLUTOS SELL
A56: Baltic new technologies
A57: AIMASA
... A73: SIA MMG Group
